{"apiVersion": 1, "apiState": 1, "apiReference": "prod", "title": "31 MART 2024 YEREL SEÇİMİ", "desc": "Yerel Seçim - İlçe Meclis", "electionType": "yerel", "updateDate": "2024-04-01T05:30:32+03:00", "data": {"city": {"id": "74", "cn": "Bartın", "cs": "Bartın", "cc": "74", "tbc": "616", "obc": "616", "obp": "100.00", "vvc": "122500", "uvc": "130497", "pp": "82.21", "i": 44, "tpc": "158737", "prts": [{"id": "18", "pid": "18", "pn": "CHP", "vp": "33.25", "vc": "40735", "i": 1, "past": {"vc": 26133, "vp": "20.96"}}, {"id": "1", "pid": "1", "pn": "AK Parti", "vp": "30.99", "vc": "37958", "i": 2, "past": {"vc": 57585, "vp": "46.19"}}, {"id": "30", "pid": "30", "pn": "MHP", "vp": "16.59", "vc": "20318", "i": 3, "past": {"vc": 28094, "vp": "22.54"}}, {"id": "8", "pid": "8", "pn": "Yeniden Refah", "vp": "9.34", "vc": "11441", "i": 4, "past": {"vc": 0, "vp": "0.00"}}, {"id": "33", "pid": "33", "pn": "Saadet", "vp": "2.30", "vc": "2818", "i": 5, "past": {"vc": 5347, "vp": "4.29"}}, {"id": "12", "pid": "12", "pn": "Zafer Partisi", "vp": "2.00", "vc": "2444", "i": 6, "past": {"vc": 0, "vp": "0.00"}}, {"id": "2", "pid": "2", "pn": "İyi Parti", "vp": "1.80", "vc": "2207", "i": 7, "past": {"vc": 5595, "vp": "4.49"}}, {"id": "32", "pid": "32", "pn": "DEVA Partisi", "vp": "0.77", "vc": "944", "i": 8, "past": {"vc": 0, "vp": "0.00"}}, {"id": "16", "pid": "16", "pn": "Gelecek Partisi", "vp": "0.43", "vc": "524", "i": 9, "past": {"vc": 0, "vp": "0.00"}}, {"id": "15", "pid": "15", "pn": "BTP", "vp": "0.42", "vc": "515", "i": 10, "past": {"vc": 234, "vp": "0.19"}}, {"id": "26", "pid": "26", "pn": "Millet", "vp": "0.39", "vc": "479", "i": 11, "past": {"vc": 0, "vp": "0.00"}}, {"id": "4", "pid": "4", "pn": "Büyük Birlik", "vp": "0.33", "vc": "404", "i": 12, "past": {"vc": 762, "vp": "0.61"}}, {"id": "31", "pid": "31", "pn": "TİP", "vp": "0.33", "vc": "402", "i": 13, "past": {"vc": 0, "vp": "0.00"}}, {"id": "3", "pid": "3", "pn": "Sol Parti", "vp": "0.29", "vc": "351", "i": 14, "past": {"vc": 0, "vp": "0.00"}}, {"id": "34", "pid": "34", "pn": "Vatan Partisi", "vp": "0.24", "vc": "295", "i": 15, "past": {"vc": 309, "vp": "0.25"}}, {"id": "20", "pid": "20", "pn": "HÜDA PAR", "vp": "0.19", "vc": "238", "i": 16, "past": {"vc": 0, "vp": "0.00"}}, {"id": "9", "pid": "9", "pn": "DEM Parti", "vp": "0.19", "vc": "227", "i": 17, "past": {"vc": 0, "vp": "0.00"}}, {"id": "19", "pid": "19", "pn": "EMEP", "vp": "0.14", "vc": "176", "i": 18, "past": {"vc": 0, "vp": "0.00"}}, {"id": "814", "pid": "814", "pn": "MEHMET BENSİZ", "vp": "0.02", "vc": "24", "i": 19, "past": {"vp": "0.00", "vc": 0}}]}, "districts": [{"id": "71", "dn": "MERKEZ", "cs": "MERKEZ", "cc": "71", "tbc": "189", "obc": "189", "obp": "100.00", "vvc": "43494", "uvc": "46225", "pp": "74.89", "i": 1, "tpc": "61720", "prts": [{"id": "18", "pid": "18", "pn": "CHP", "vp": "50.77", "vc": "22081", "i": 1, "past": {"vc": 18658, "vp": "19.93"}}, {"id": "30", "pid": "30", "pn": "MHP", "vp": "33.51", "vc": "14574", "i": 2, "past": {"vc": 23446, "vp": "25.05"}}, {"id": "8", "pid": "8", "pn": "Yeniden Refah", "vp": "6.04", "vc": "2626", "i": 3, "past": {"vc": 0, "vp": "0.00"}}, {"id": "2", "pid": "2", "pn": "İyi Parti", "vp": "3.46", "vc": "1506", "i": 4, "past": {"vc": 4009, "vp": "4.28"}}, {"id": "12", "pid": "12", "pn": "Zafer Partisi", "vp": "3.03", "vc": "1318", "i": 5, "past": {"vc": 0, "vp": "0.00"}}, {"id": "33", "pid": "33", "pn": "Saadet", "vp": "1.28", "vc": "555", "i": 6, "past": {"vc": 4334, "vp": "4.63"}}, {"id": "16", "pid": "16", "pn": "Gelecek Partisi", "vp": "0.85", "vc": "368", "i": 7, "past": {"vc": 0, "vp": "0.00"}}, {"id": "32", "pid": "32", "pn": "DEVA Partisi", "vp": "0.45", "vc": "195", "i": 8, "past": {"vc": 0, "vp": "0.00"}}, {"id": "10", "pid": "10", "pn": "TKP", "vp": "0.34", "vc": "147", "i": 9, "past": {"vc": 0, "vp": "0.00"}}, {"id": "15", "pid": "15", "pn": "BTP", "vp": "0.29", "vc": "124", "i": 10, "past": {"vc": 158, "vp": "0.17"}}]}, {"id": "389", "dn": "KURUCAŞİLE", "cs": "KURUCAŞİLE", "cc": "389", "tbc": "6", "obc": "6", "obp": "100.00", "vvc": "1218", "uvc": "1287", "pp": "84.28", "i": 4, "tpc": "1527", "prts": [{"id": "18", "pid": "18", "pn": "CHP", "vp": "49.26", "vc": "600", "i": 1, "past": {"vc": 1466, "vp": "29.92"}}, {"id": "1", "pid": "1", "pn": "AK Parti", "vp": "42.28", "vc": "515", "i": 2, "past": {"vc": 2261, "vp": "46.14"}}, {"id": "10", "pid": "10", "pn": "TKP", "vp": "6.32", "vc": "77", "i": 3, "past": {"vc": 0, "vp": "0.00"}}, {"id": "8", "pid": "8", "pn": "Yeniden Refah", "vp": "1.07", "vc": "13", "i": 4, "past": {"vc": 0, "vp": "0.00"}}, {"id": "12", "pid": "12", "pn": "Zafer Partisi", "vp": "0.66", "vc": "8", "i": 5, "past": {"vc": 0, "vp": "0.00"}}, {"id": "15", "pid": "15", "pn": "BTP", "vp": "0.41", "vc": "5", "i": 6, "past": {"vc": 12, "vp": "0.24"}}]}, {"id": "594", "dn": "ULUS", "cs": "ULUS", "cc": "594", "tbc": "10", "obc": "10", "obp": "100.00", "vvc": "2253", "uvc": "2418", "pp": "81.94", "i": 5, "tpc": "2951", "prts": [{"id": "1", "pid": "1", "pn": "AK Parti", "vp": "50.51", "vc": "1138", "i": 1, "past": {"vc": 9749, "vp": "59.66"}}, {"id": "18", "pid": "18", "pn": "CHP", "vp": "39.41", "vc": "888", "i": 2, "past": {"vc": 2872, "vp": "17.57"}}, {"id": "12", "pid": "12", "pn": "Zafer Partisi", "vp": "2.84", "vc": "64", "i": 3, "past": {"vc": 0, "vp": "0.00"}}, {"id": "15", "pid": "15", "pn": "BTP", "vp": "2.40", "vc": "54", "i": 4, "past": {"vc": 45, "vp": "0.28"}}, {"id": "33", "pid": "33", "pn": "Saadet", "vp": "2.35", "vc": "53", "i": 5, "past": {"vc": 546, "vp": "3.34"}}, {"id": "8", "pid": "8", "pn": "Yeniden Refah", "vp": "2.17", "vc": "49", "i": 6, "past": {"vc": 0, "vp": "0.00"}}, {"id": "10", "pid": "10", "pn": "TKP", "vp": "0.31", "vc": "7", "i": 7, "past": {"vc": 0, "vp": "0.00"}}]}, {"id": "654", "dn": "AMASRA", "cs": "AMASRA", "cc": "654", "tbc": "17", "obc": "17", "obp": "100.00", "vvc": "3895", "uvc": "4079", "pp": "81.01", "i": 8, "tpc": "5035", "prts": [{"id": "18", "pid": "18", "pn": "CHP", "vp": "48.14", "vc": "1875", "i": 1, "past": {"vc": 3137, "vp": "31.97"}}, {"id": "1", "pid": "1", "pn": "AK Parti", "vp": "39.31", "vc": "1531", "i": 2, "past": {"vc": 3908, "vp": "39.82"}}, {"id": "32", "pid": "32", "pn": "DEVA Partisi", "vp": "7.57", "vc": "295", "i": 3, "past": {"vc": 0, "vp": "0.00"}}, {"id": "12", "pid": "12", "pn": "Zafer Partisi", "vp": "2.03", "vc": "79", "i": 4, "past": {"vc": 0, "vp": "0.00"}}, {"id": "8", "pid": "8", "pn": "Yeniden Refah", "vp": "1.54", "vc": "60", "i": 5, "past": {"vc": 0, "vp": "0.00"}}, {"id": "10", "pid": "10", "pn": "TKP", "vp": "0.59", "vc": "23", "i": 6, "past": {"vc": 0, "vp": "0.00"}}, {"id": "33", "pid": "33", "pn": "Saadet", "vp": "0.49", "vc": "19", "i": 7, "past": {"vc": 243, "vp": "2.48"}}, {"id": "15", "pid": "15", "pn": "BTP", "vp": "0.33", "vc": "13", "i": 8, "past": {"vc": 19, "vp": "0.19"}}]}], "towns": [{"id": "2971", "dn": "MERKEZ-HASANKADI", "cs": "MERKEZ-HASANKADI", "cc": "2971", "tbc": "7", "obc": "6", "obp": "85.71", "vvc": "1245", "uvc": "1367", "pp": "76.37", "i": 2, "tpc": "1790", "prts": [{"id": "1", "cid": "1", "cn": "AK Parti", "pid": "1", "pn": "AK Parti", "vp": "41.93", "vc": "522", "i": 1, "past": []}, {"id": "30", "cid": "30", "cn": "MHP", "pid": "30", "pn": "MHP", "vp": "38.47", "vc": "479", "i": 2, "past": []}, {"id": "18", "cid": "18", "cn": "CHP", "pid": "18", "pn": "CHP", "vp": "11.57", "vc": "144", "i": 3, "past": []}, {"id": "8", "cid": "8", "cn": "Yeniden Refah", "pid": "8", "pn": "Yeniden Refah", "vp": "2.57", "vc": "32", "i": 4, "past": []}, {"id": "33", "cid": "33", "cn": "Saadet", "pid": "33", "pn": "Saadet", "vp": "0.88", "vc": "11", "i": 5, "past": []}, {"id": "12", "cid": "12", "cn": "Zafer Partisi", "pid": "12", "pn": "Zafer Partisi", "vp": "0.32", "vc": "4", "i": 6, "past": []}, {"id": "0", "cid": "0", "cn": "Diğer", "pid": "0", "pn": "Diğer", "vp": "4.26", "vc": "53", "i": 7, "past": []}]}, {"id": "2972", "dn": "MERKEZ-KOZCAĞIZ", "cs": "MERKEZ-KOZCAĞIZ", "cc": "2972", "tbc": "18", "obc": "4", "obp": "22.22", "vvc": "1014", "uvc": "1077", "pp": "19.39", "i": 3, "tpc": "5554", "prts": [{"id": "30", "cid": "30", "cn": "MHP", "pid": "30", "pn": "MHP", "vp": "36.09", "vc": "366", "i": 1, "past": []}, {"id": "1", "cid": "1", "cn": "AK Parti", "pid": "1", "pn": "AK Parti", "vp": "31.26", "vc": "317", "i": 2, "past": []}, {"id": "18", "cid": "18", "cn": "CHP", "pid": "18", "pn": "CHP", "vp": "18.34", "vc": "186", "i": 3, "past": []}, {"id": "33", "cid": "33", "cn": "Saadet", "pid": "33", "pn": "Saadet", "vp": "8.88", "vc": "90", "i": 4, "past": []}, {"id": "8", "cid": "8", "cn": "Yeniden Refah", "pid": "8", "pn": "Yeniden Refah", "vp": "4.14", "vc": "42", "i": 5, "past": []}, {"id": "12", "cid": "12", "cn": "Zafer Partisi", "pid": "12", "pn": "Zafer Partisi", "vp": "1.28", "vc": "13", "i": 6, "past": []}]}, {"id": "2973", "dn": "ULUS-ABDİPAŞA", "cs": "ULUS-ABDİPAŞA", "cc": "2973", "tbc": "9", "obc": "6", "obp": "66.67", "vvc": "1312", "uvc": "1415", "pp": "62.47", "i": 6, "tpc": "2265", "prts": [{"id": "1", "cid": "1", "cn": "AK Parti", "pid": "1", "pn": "AK Parti", "vp": "37.96", "vc": "498", "i": 1, "past": []}, {"id": "30", "cid": "30", "cn": "MHP", "pid": "30", "pn": "MHP", "vp": "33.99", "vc": "446", "i": 2, "past": []}, {"id": "18", "cid": "18", "cn": "CHP", "pid": "18", "pn": "CHP", "vp": "14.02", "vc": "184", "i": 3, "past": []}, {"id": "8", "cid": "8", "cn": "Yeniden Refah", "pid": "8", "pn": "Yeniden Refah", "vp": "12.12", "vc": "159", "i": 4, "past": []}, {"id": "2", "cid": "2", "cn": "İyi Parti", "pid": "2", "pn": "İyi Parti", "vp": "0.99", "vc": "13", "i": 5, "past": []}, {"id": "12", "cid": "12", "cn": "Zafer Partisi", "pid": "12", "pn": "Zafer Partisi", "vp": "0.91", "vc": "12", "i": 6, "past": []}]}, {"id": "2974", "dn": "ULUS-KUMLUCA", "cs": "ULUS-KUMLUCA", "cc": "2974", "tbc": "6", "obc": "3", "obp": "50.00", "vvc": "713", "uvc": "758", "pp": "43.46", "i": 7, "tpc": "1744", "prts": [{"id": "1", "cid": "1", "cn": "AK Parti", "pid": "1", "pn": "AK Parti", "vp": "43.06", "vc": "307", "i": 1, "past": []}, {"id": "33", "cid": "33", "cn": "Saadet", "pid": "33", "pn": "Saadet", "vp": "33.24", "vc": "237", "i": 2, "past": []}, {"id": "30", "cid": "30", "cn": "MHP", "pid": "30", "pn": "MHP", "vp": "18.09", "vc": "129", "i": 3, "past": []}, {"id": "8", "cid": "8", "cn": "Yeniden Refah", "pid": "8", "pn": "Yeniden Refah", "vp": "4.49", "vc": "32", "i": 4, "past": []}, {"id": "12", "cid": "12", "cn": "Zafer Partisi", "pid": "12", "pn": "Zafer Partisi", "vp": "1.12", "vc": "8", "i": 5, "past": []}]}]}}