{"cityChest": {"totalChest": 389, "totalOpenChestPercent": 100, "openChest": 389, "totalVoter": 129084, "totalVote": 102127, "validVote": 99116, "invalidVote": 3011, "totalJoinPercent": 79.11669920361935}, "partyMap": [{"chest": {"totalChest": 12, "totalOpenChestPercent": 100, "openChest": 12, "totalVoter": 3581, "totalVote": 3092, "validVote": 3002, "invalidVote": 90, "totalJoinPercent": 86.34459648142978}, "details": [{"candidate": {"no": "0", "name": "Özkan Günenç", "partyNo": "21", "url": "/chp/edirne/enez/ozkan-gunenc-belediye-baskani-adayi/"}, "previousTotalVote": null, "previousTotalVotePercent": null, "no": 21, "name": "CHP", "totalVote": 1590, "totalVotePercent": 52.96469020652898, "url": "/chp-yerel-secim-sonuclari/"}, {"candidate": {"no": "0", "name": "Abdullah Bostancı", "partyNo": "9", "url": "/ak-parti/edirne/enez/abdullah-bostanci-belediye-baskani-adayi/"}, "previousTotalVote": null, "previousTotalVotePercent": null, "no": 9, "name": "AK Parti", "totalVote": 1133, "totalVotePercent": 37.741505662891406, "url": "/ak-parti-yerel-secim-sonuclari/"}], "winner": {"candidate": {"no": "0", "name": "Özkan Günenç", "partyNo": "21", "url": "/chp/edirne/enez/ozkan-gunenc-belediye-baskani-adayi/"}, "previousTotalVote": null, "previousTotalVotePercent": null, "no": 21, "name": "CHP", "totalVote": 1590, "totalVotePercent": 52.96469020652898, "url": "/chp-yerel-secim-sonuclari/"}, "previousWinner": null, "councilPartySummaries": [], "allParties": null, "towns": [], "no": 205, "name": "ENEZ", "totalVote": 0, "totalVotePercent": 0, "url": "/edirne-enez-ilcesi-yerel-secim-sonuclari/"}, {"chest": {"totalChest": 22, "totalOpenChestPercent": 100, "openChest": 22, "totalVoter": 7049, "totalVote": 6069, "validVote": 5842, "invalidVote": 227, "totalJoinPercent": 86.09731876861966}, "details": [{"candidate": {"no": "0", "name": "Hüseyin Özden", "partyNo": "21", "url": "/chp/edirne/havsa/huseyin-ozden-belediye-baskani-adayi/"}, "previousTotalVote": null, "previousTotalVotePercent": null, "no": 21, "name": "CHP", "totalVote": 3253, "totalVotePercent": 55.682985279014034, "url": "/chp-yerel-secim-sonuclari/"}, {"candidate": {"no": "0", "name": "Aydın Balkan", "partyNo": "9", "url": "/ak-parti/edirne/havsa/aydin-balkan-belediye-baskani-adayi/"}, "previousTotalVote": null, "previousTotalVotePercent": null, "no": 9, "name": "AK Parti", "totalVote": 2285, "totalVotePercent": 39.1133173570695, "url": "/ak-parti-yerel-secim-sonuclari/"}], "winner": {"candidate": {"no": "0", "name": "Hüseyin Özden", "partyNo": "21", "url": "/chp/edirne/havsa/huseyin-ozden-belediye-baskani-adayi/"}, "previousTotalVote": null, "previousTotalVotePercent": null, "no": 21, "name": "CHP", "totalVote": 3253, "totalVotePercent": 55.682985279014034, "url": "/chp-yerel-secim-sonuclari/"}, "previousWinner": null, "councilPartySummaries": [], "allParties": null, "towns": [], "no": 282, "name": "HAVSA", "totalVote": 0, "totalVotePercent": 0, "url": "/edirne-havsa-ilcesi-yerel-secim-sonuclari/"}, {"chest": {"totalChest": 21, "totalOpenChestPercent": 100, "openChest": 21, "totalVoter": 6356, "totalVote": 5675, "validVote": 5474, "invalidVote": 201, "totalJoinPercent": 89.28571428571429}, "details": [{"candidate": {"no": "0", "name": "Mehmet Kerman", "partyNo": "9", "url": "/ak-parti/edirne/ipsala/mehmet-kerman-belediye-baskani-adayi/"}, "previousTotalVote": null, "previousTotalVotePercent": null, "no": 9, "name": "AK Parti", "totalVote": 1645, "totalVotePercent": 30.051150895140665, "url": "/ak-parti-yerel-secim-sonuclari/"}, {"candidate": {"no": "0", "name": "Cenan Tetik", "partyNo": "21", "url": "/chp/edirne/ipsala/cenan-tetik-belediye-baskani-adayi/"}, "previousTotalVote": null, "previousTotalVotePercent": null, "no": 21, "name": "CHP", "totalVote": 1533, "totalVotePercent": 28.005115089514067, "url": "/chp-yerel-secim-sonuclari/"}], "winner": {"candidate": {"no": "0", "name": "Mehmet Kerman", "partyNo": "9", "url": "/ak-parti/edirne/ipsala/mehmet-kerman-belediye-baskani-adayi/"}, "previousTotalVote": null, "previousTotalVotePercent": null, "no": 9, "name": "AK Parti", "totalVote": 1645, "totalVotePercent": 30.051150895140665, "url": "/ak-parti-yerel-secim-sonuclari/"}, "previousWinner": null, "councilPartySummaries": [], "allParties": null, "towns": [], "no": 309, "name": "İPSALA", "totalVote": 0, "totalVotePercent": 0, "url": "/edirne-ipsala-ilcesi-yerel-secim-sonuclari/"}, {"chest": {"totalChest": 6, "totalOpenChestPercent": 100, "openChest": 6, "totalVoter": 1738, "totalVote": 1687, "validVote": 1579, "invalidVote": 108, "totalJoinPercent": 97.0655926352129}, "details": [{"candidate": null, "previousTotalVote": null, "previousTotalVotePercent": null, "no": 9, "name": "AK Parti", "totalVote": 839, "totalVotePercent": 53.134895503483214, "url": "/ak-parti-yerel-secim-sonuclari/"}, {"candidate": null, "previousTotalVote": null, "previousTotalVotePercent": null, "no": 21, "name": "CHP", "totalVote": 732, "totalVotePercent": 46.35845471817606, "url": "/chp-yerel-secim-sonuclari/"}], "winner": {"candidate": null, "previousTotalVote": null, "previousTotalVotePercent": null, "no": 9, "name": "AK Parti", "totalVote": 839, "totalVotePercent": 53.134895503483214, "url": "/ak-parti-yerel-secim-sonuclari/"}, "previousWinner": null, "councilPartySummaries": [], "allParties": null, "towns": [], "no": 4852, "name": "İPSALA-ESETÇE", "totalVote": 0, "totalVotePercent": 0, "url": "/edirne-ipsala-esetce-ilcesi-yerel-secim-sonuclari/"}, {"chest": {"totalChest": 8, "totalOpenChestPercent": 100, "openChest": 8, "totalVoter": 2416, "totalVote": 2294, "validVote": 2186, "invalidVote": 108, "totalJoinPercent": 94.95033112582782}, "details": [{"candidate": null, "previousTotalVote": null, "previousTotalVotePercent": null, "no": 21, "name": "CHP", "totalVote": 1386, "totalVotePercent": 63.403476669716376, "url": "/chp-yerel-secim-sonuclari/"}, {"candidate": null, "previousTotalVote": null, "previousTotalVotePercent": null, "no": 9, "name": "AK Parti", "totalVote": 781, "totalVotePercent": 35.727355901189384, "url": "/ak-parti-yerel-secim-sonuclari/"}], "winner": {"candidate": null, "previousTotalVote": null, "previousTotalVotePercent": null, "no": 21, "name": "CHP", "totalVote": 1386, "totalVotePercent": 63.403476669716376, "url": "/chp-yerel-secim-sonuclari/"}, "previousWinner": null, "councilPartySummaries": [], "allParties": null, "towns": [], "no": 4850, "name": "İPSALA-YENİKARPUZLU", "totalVote": 0, "totalVotePercent": 0, "url": "/edirne-ipsala-yenikarpuzlu-ilcesi-yerel-secim-sonuclari/"}, {"chest": {"totalChest": 149, "totalOpenChestPercent": 100, "openChest": 149, "totalVoter": 49031, "totalVote": 40226, "validVote": 38913, "invalidVote": 1313, "totalJoinPercent": 82.0419734453713}, "details": [{"candidate": {"no": "0", "name": "Mehmet Özcan", "partyNo": "21", "url": "/chp/edirne/kesan/mehmet-ozcan-belediye-baskani-adayi/"}, "previousTotalVote": null, "previousTotalVotePercent": null, "no": 21, "name": "CHP", "totalVote": 20667, "totalVotePercent": 53.110785598643126, "url": "/chp-yerel-secim-sonuclari/"}, {"candidate": {"no": "0", "name": "Mustafa Helvacıoğlu", "partyNo": "9", "url": "/ak-parti/edirne/kesan/mustafa-helvacioglu-belediye-baskani-adayi/"}, "previousTotalVote": null, "previousTotalVotePercent": null, "no": 9, "name": "AK Parti", "totalVote": 16139, "totalVotePercent": 41.474571479968134, "url": "/ak-parti-yerel-secim-sonuclari/"}], "winner": {"candidate": {"no": "0", "name": "Mehmet Özcan", "partyNo": "21", "url": "/chp/edirne/kesan/mehmet-ozcan-belediye-baskani-adayi/"}, "previousTotalVote": null, "previousTotalVotePercent": null, "no": 21, "name": "CHP", "totalVote": 20667, "totalVotePercent": 53.110785598643126, "url": "/chp-yerel-secim-sonuclari/"}, "previousWinner": null, "councilPartySummaries": [], "allParties": null, "towns": [], "no": 358, "name": "KEŞAN", "totalVote": 0, "totalVotePercent": 0, "url": "/edirne-kesan-ilcesi-yerel-secim-sonuclari/"}, {"chest": {"totalChest": 9, "totalOpenChestPercent": 100, "openChest": 9, "totalVoter": 2689, "totalVote": 2447, "validVote": 2355, "invalidVote": 92, "totalJoinPercent": 91.00037188545927}, "details": [{"candidate": null, "previousTotalVote": null, "previousTotalVotePercent": null, "no": 9, "name": "AK Parti", "totalVote": 1219, "totalVotePercent": 51.76220806794055, "url": "/ak-parti-yerel-secim-sonuclari/"}, {"candidate": null, "previousTotalVote": null, "previousTotalVotePercent": null, "no": 21, "name": "CHP", "totalVote": 1114, "totalVotePercent": 47.303609341825904, "url": "/chp-yerel-secim-sonuclari/"}], "winner": {"candidate": null, "previousTotalVote": null, "previousTotalVotePercent": null, "no": 9, "name": "AK Parti", "totalVote": 1219, "totalVotePercent": 51.76220806794055, "url": "/ak-parti-yerel-secim-sonuclari/"}, "previousWinner": null, "councilPartySummaries": [], "allParties": null, "towns": [], "no": 4857, "name": "KEŞAN-BEĞENDİK", "totalVote": 0, "totalVotePercent": 0, "url": "/edirne-kesan-begendik-ilcesi-yerel-secim-sonuclari/"}, {"chest": {"totalChest": 7, "totalOpenChestPercent": 100, "openChest": 7, "totalVoter": 1682, "totalVote": 1580, "validVote": 1532, "invalidVote": 48, "totalJoinPercent": 93.935790725327}, "details": [{"candidate": null, "previousTotalVote": null, "previousTotalVotePercent": null, "no": 21, "name": "CHP", "totalVote": 830, "totalVotePercent": 54.177545691906005, "url": "/chp-yerel-secim-sonuclari/"}, {"candidate": null, "previousTotalVote": null, "previousTotalVotePercent": null, "no": 9, "name": "AK Parti", "totalVote": 702, "totalVotePercent": 45.822454308093995, "url": "/ak-parti-yerel-secim-sonuclari/"}], "winner": {"candidate": null, "previousTotalVote": null, "previousTotalVotePercent": null, "no": 21, "name": "CHP", "totalVote": 830, "totalVotePercent": 54.177545691906005, "url": "/chp-yerel-secim-sonuclari/"}, "previousWinner": null, "councilPartySummaries": [], "allParties": null, "towns": [], "no": 4854, "name": "KEŞAN-YENİMUHACİR", "totalVote": 0, "totalVotePercent": 0, "url": "/edirne-kesan-yenimuhacir-ilcesi-yerel-secim-sonuclari/"}, {"chest": {"totalChest": 4, "totalOpenChestPercent": 100, "openChest": 4, "totalVoter": 1224, "totalVote": 1121, "validVote": 1057, "invalidVote": 64, "totalJoinPercent": 91.58496732026144}, "details": [{"candidate": {"no": "0", "name": "Zafer Sezgin Geldi", "partyNo": "21", "url": "/chp/edirne/lalapasa/zafer-sezgin-geldi-belediye-baskani-adayi/"}, "previousTotalVote": null, "previousTotalVotePercent": null, "no": 21, "name": "CHP", "totalVote": 554, "totalVotePercent": 52.41248817407758, "url": "/chp-yerel-secim-sonuclari/"}, {"candidate": {"no": "0", "name": "İsmail Arslan", "partyNo": "9", "url": "/ak-parti/edirne/lalapasa/ismail-arslan-belediye-baskani-adayi/"}, "previousTotalVote": null, "previousTotalVotePercent": null, "no": 9, "name": "AK Parti", "totalVote": 406, "totalVotePercent": 38.41059602649007, "url": "/ak-parti-yerel-secim-sonuclari/"}], "winner": {"candidate": {"no": "0", "name": "Zafer Sezgin Geldi", "partyNo": "21", "url": "/chp/edirne/lalapasa/zafer-sezgin-geldi-belediye-baskani-adayi/"}, "previousTotalVote": null, "previousTotalVotePercent": null, "no": 21, "name": "CHP", "totalVote": 554, "totalVotePercent": 52.41248817407758, "url": "/chp-yerel-secim-sonuclari/"}, "previousWinner": null, "councilPartySummaries": [], "allParties": null, "towns": [], "no": 395, "name": "LALAPAŞA", "totalVote": 0, "totalVotePercent": 0, "url": "/edirne-lalapasa-ilcesi-yerel-secim-sonuclari/"}, {"chest": {"totalChest": 8, "totalOpenChestPercent": 100, "openChest": 8, "totalVoter": 2055, "totalVote": 1753, "validVote": 1642, "invalidVote": 111, "totalJoinPercent": 85.30413625304136}, "details": [{"candidate": {"no": "0", "name": "Yunus Atay", "partyNo": "9", "url": "/ak-parti/edirne/meric/yunus-atay-belediye-baskani-adayi/"}, "previousTotalVote": null, "previousTotalVotePercent": null, "no": 9, "name": "AK Parti", "totalVote": 719, "totalVotePercent": 43.788063337393424, "url": "/ak-parti-yerel-secim-sonuclari/"}, {"candidate": {"no": "0", "name": "Erol Dübek", "partyNo": "21", "url": "/chp/edirne/meric/erol-dubek-belediye-baskani-adayi/"}, "previousTotalVote": null, "previousTotalVotePercent": null, "no": 21, "name": "CHP", "totalVote": 596, "totalVotePercent": 36.297198538367844, "url": "/chp-yerel-secim-sonuclari/"}], "winner": {"candidate": {"no": "0", "name": "Yunus Atay", "partyNo": "9", "url": "/ak-parti/edirne/meric/yunus-atay-belediye-baskani-adayi/"}, "previousTotalVote": null, "previousTotalVotePercent": null, "no": 9, "name": "AK Parti", "totalVote": 719, "totalVotePercent": 43.788063337393424, "url": "/ak-parti-yerel-secim-sonuclari/"}, "previousWinner": null, "councilPartySummaries": [], "allParties": null, "towns": [], "no": 416, "name": "MERİÇ", "totalVote": 0, "totalVotePercent": 0, "url": "/edirne-meric-ilcesi-yerel-secim-sonuclari/"}, {"chest": {"totalChest": 7, "totalOpenChestPercent": 100, "openChest": 7, "totalVoter": 1994, "totalVote": 1845, "validVote": 1743, "invalidVote": 102, "totalJoinPercent": 92.52758274824474}, "details": [{"candidate": null, "previousTotalVote": null, "previousTotalVotePercent": null, "no": 21, "name": "CHP", "totalVote": 892, "totalVotePercent": 51.176133103843945, "url": "/chp-yerel-secim-sonuclari/"}, {"candidate": null, "previousTotalVote": null, "previousTotalVotePercent": null, "no": 9, "name": "AK Parti", "totalVote": 632, "totalVotePercent": 36.25932300631096, "url": "/ak-parti-yerel-secim-sonuclari/"}], "winner": {"candidate": null, "previousTotalVote": null, "previousTotalVotePercent": null, "no": 21, "name": "CHP", "totalVote": 892, "totalVotePercent": 51.176133103843945, "url": "/chp-yerel-secim-sonuclari/"}, "previousWinner": null, "councilPartySummaries": [], "allParties": null, "towns": [], "no": 4858, "name": "MERİÇ-KÜPLÜ", "totalVote": 0, "totalVotePercent": 0, "url": "/edirne-meric-kuplu-ilcesi-yerel-secim-sonuclari/"}, {"chest": {"totalChest": 5, "totalOpenChestPercent": 100, "openChest": 5, "totalVoter": 1638, "totalVote": 1528, "validVote": 1451, "invalidVote": 77, "totalJoinPercent": 93.28449328449328}, "details": [{"candidate": null, "previousTotalVote": null, "previousTotalVotePercent": null, "no": 9, "name": "AK Parti", "totalVote": 622, "totalVotePercent": 42.866988283942106, "url": "/ak-parti-yerel-secim-sonuclari/"}, {"candidate": null, "previousTotalVote": null, "previousTotalVotePercent": null, "no": 22, "name": "İYİ Parti", "totalVote": 426, "totalVotePercent": 29.35906271536871, "url": "/iyi-parti-yerel-secim-sonuclari/"}], "winner": {"candidate": null, "previousTotalVote": null, "previousTotalVotePercent": null, "no": 9, "name": "AK Parti", "totalVote": 622, "totalVotePercent": 42.866988283942106, "url": "/ak-parti-yerel-secim-sonuclari/"}, "previousWinner": null, "councilPartySummaries": [], "allParties": null, "towns": [], "no": 4859, "name": "MERİÇ-SUBAŞI", "totalVote": 0, "totalVotePercent": 0, "url": "/edirne-meric-subasi-ilcesi-yerel-secim-sonuclari/"}, {"chest": {"totalChest": 389, "totalOpenChestPercent": 100, "openChest": 389, "totalVoter": 129084, "totalVote": 102127, "validVote": 99116, "invalidVote": 3011, "totalJoinPercent": 79.11669920361935}, "details": [{"candidate": {"no": "0", "name": "Filiz Gencan Akın", "partyNo": "21", "url": "/chp/edirne/merkez/filiz-gencan-akin-belediye-baskani-adayi/"}, "previousTotalVote": null, "previousTotalVotePercent": null, "no": 21, "name": "CHP", "totalVote": 46260, "totalVotePercent": 46.67258565720974, "url": "/chp-yerel-secim-sonuclari/"}, {"candidate": {"no": "0", "name": "Belgin İba", "partyNo": "9", "url": "/ak-parti/edirne/merkez/belgin-iba-belediye-baskani-adayi/"}, "previousTotalVote": null, "previousTotalVotePercent": null, "no": 9, "name": "AK Parti", "totalVote": 42119, "totalVotePercent": 42.49465273013439, "url": "/ak-parti-yerel-secim-sonuclari/"}], "winner": {"candidate": {"no": "0", "name": "Filiz Gencan Akın", "partyNo": "21", "url": "/chp/edirne/merkez/filiz-gencan-akin-belediye-baskani-adayi/"}, "previousTotalVote": null, "previousTotalVotePercent": null, "no": 21, "name": "CHP", "totalVote": 46260, "totalVotePercent": 46.67258565720974, "url": "/chp-yerel-secim-sonuclari/"}, "previousWinner": null, "councilPartySummaries": [], "allParties": null, "towns": [], "no": 193, "name": "MERKEZ", "totalVote": 0, "totalVotePercent": 0, "url": "/edirne-merkez-ilcesi-yerel-secim-sonuclari/"}, {"chest": {"totalChest": 7, "totalOpenChestPercent": 100, "openChest": 7, "totalVoter": 2206, "totalVote": 1793, "validVote": 1724, "invalidVote": 69, "totalJoinPercent": 81.27833182230282}, "details": [{"candidate": {"no": "0", "name": "Mehmet Ormankıran", "partyNo": "21", "url": "/chp/edirne/suloglu/mehmet-ormankiran-belediye-baskani-adayi/"}, "previousTotalVote": null, "previousTotalVotePercent": null, "no": 21, "name": "CHP", "totalVote": 1080, "totalVotePercent": 62.64501160092807, "url": "/chp-yerel-secim-sonuclari/"}, {"candidate": {"no": "0", "name": "Halil Özgüven", "partyNo": "11", "url": "/mhp/edirne/suloglu/halil-ozguven-belediye-baskani-adayi/"}, "previousTotalVote": null, "previousTotalVotePercent": null, "no": 11, "name": "MHP", "totalVote": 472, "totalVotePercent": 27.378190255220417, "url": "/mhp-yerel-secim-sonuclari/"}], "winner": {"candidate": {"no": "0", "name": "Mehmet Ormankıran", "partyNo": "21", "url": "/chp/edirne/suloglu/mehmet-ormankiran-belediye-baskani-adayi/"}, "previousTotalVote": null, "previousTotalVotePercent": null, "no": 21, "name": "CHP", "totalVote": 1080, "totalVotePercent": 62.64501160092807, "url": "/chp-yerel-secim-sonuclari/"}, "previousWinner": null, "councilPartySummaries": [], "allParties": null, "towns": [], "no": 881, "name": "SÜLOĞLU", "totalVote": 0, "totalVotePercent": 0, "url": "/edirne-suloglu-ilcesi-yerel-secim-sonuclari/"}, {"chest": {"totalChest": 96, "totalOpenChestPercent": 100, "openChest": 96, "totalVoter": 30978, "totalVote": 25122, "validVote": 24153, "invalidVote": 969, "totalJoinPercent": 81.0962618632578}, "details": [{"candidate": {"no": "0", "name": "Ediz Martin", "partyNo": "22", "url": "/iyi-parti/edirne/uzunkopru/ediz-martin-belediye-baskani-adayi/"}, "previousTotalVote": null, "previousTotalVotePercent": null, "no": 22, "name": "İYİ Parti", "totalVote": 8026, "totalVotePercent": 33.229826522585185, "url": "/iyi-parti-yerel-secim-sonuclari/"}, {"candidate": {"no": "0", "name": "Özlem Becan", "partyNo": "21", "url": "/chp/edirne/uzunkopru/ozlem-becan-belediye-baskani-adayi/"}, "previousTotalVote": null, "previousTotalVotePercent": null, "no": 21, "name": "CHP", "totalVote": 7941, "totalVotePercent": 32.87790336604149, "url": "/chp-yerel-secim-sonuclari/"}], "winner": {"candidate": {"no": "0", "name": "Ediz Martin", "partyNo": "22", "url": "/iyi-parti/edirne/uzunkopru/ediz-martin-belediye-baskani-adayi/"}, "previousTotalVote": null, "previousTotalVotePercent": null, "no": 22, "name": "İYİ Parti", "totalVote": 8026, "totalVotePercent": 33.229826522585185, "url": "/iyi-parti-yerel-secim-sonuclari/"}, "previousWinner": null, "councilPartySummaries": [], "allParties": null, "towns": [], "no": 598, "name": "UZUNKÖPRÜ", "totalVote": 0, "totalVotePercent": 0, "url": "/edirne-uzunkopru-ilcesi-yerel-secim-sonuclari/"}, {"chest": {"totalChest": 8, "totalOpenChestPercent": 100, "openChest": 8, "totalVoter": 2254, "totalVote": 2109, "validVote": 1978, "invalidVote": 131, "totalJoinPercent": 93.56699201419698}, "details": [{"candidate": null, "previousTotalVote": null, "previousTotalVotePercent": null, "no": 9, "name": "AK Parti", "totalVote": 1036, "totalVotePercent": 52.376137512639026, "url": "/ak-parti-yerel-secim-sonuclari/"}, {"candidate": null, "previousTotalVote": null, "previousTotalVotePercent": null, "no": 21, "name": "CHP", "totalVote": 899, "totalVotePercent": 45.44994944388271, "url": "/chp-yerel-secim-sonuclari/"}], "winner": {"candidate": null, "previousTotalVote": null, "previousTotalVotePercent": null, "no": 9, "name": "AK Parti", "totalVote": 1036, "totalVotePercent": 52.376137512639026, "url": "/ak-parti-yerel-secim-sonuclari/"}, "previousWinner": null, "councilPartySummaries": [], "allParties": null, "towns": [], "no": 4862, "name": "UZUNKÖPRÜ-KIRCASALİH", "totalVote": 0, "totalVotePercent": 0, "url": "/edirne-uzunkopru-kircasalih-ilcesi-yerel-secim-sonuclari/"}], "partyTableMap": [{"chest": {"totalChest": 12, "totalOpenChestPercent": 100, "openChest": 12, "totalVoter": 3581, "totalVote": 3092, "validVote": 3002, "invalidVote": 90, "totalJoinPercent": 86.34459648142978}, "details": [{"candidate": null, "previousTotalVote": 0, "previousTotalVotePercent": 0, "no": 9, "name": "AK Parti", "totalVote": 1133, "totalVotePercent": 37.741505662891406, "url": "/ak-parti-yerel-secim-sonuclari/"}, {"candidate": null, "previousTotalVote": 0, "previousTotalVotePercent": 0, "no": 11, "name": "MHP", "totalVote": 27, "totalVotePercent": 0.899400399733511, "url": "/mhp-yerel-secim-sonuclari/"}, {"candidate": null, "previousTotalVote": 0, "previousTotalVotePercent": 0, "no": 21, "name": "CHP", "totalVote": 1590, "totalVotePercent": 52.96469020652898, "url": "/chp-yerel-secim-sonuclari/"}, {"candidate": null, "previousTotalVote": 0, "previousTotalVotePercent": 0, "no": 10, "name": "Yeniden Refah", "totalVote": 0, "totalVotePercent": 0, "url": "/yeniden-refah-yerel-secim-sonuclari/"}, {"candidate": null, "previousTotalVote": 0, "previousTotalVotePercent": 0, "no": 87, "name": "DEM Parti", "totalVote": 0, "totalVotePercent": 0, "url": "/dem-parti-yerel-secim-sonuclari/"}, {"candidate": null, "previousTotalVote": 0, "previousTotalVotePercent": 0, "no": 0, "name": "Diğer", "totalVote": 252, "totalVotePercent": 8.394403730846102, "url": ""}], "winner": {"candidate": {"no": "0", "name": "Özkan Günenç", "partyNo": "21", "url": "/chp/edirne/enez/ozkan-gunenc-belediye-baskani-adayi/"}, "previousTotalVote": 0, "previousTotalVotePercent": 0, "no": 21, "name": "CHP", "totalVote": 1590, "totalVotePercent": 52.96469020652898, "url": "/chp-yerel-secim-sonuclari/"}, "previousWinner": {"candidate": {"no": "0", "name": "Özkan Günenç", "partyNo": "21", "url": null}, "previousTotalVote": 0, "previousTotalVotePercent": 0, "no": 21, "name": "CHP", "totalVote": 1743, "totalVotePercent": 58.64737550471063, "url": "/chp-yerel-secim-sonuclari/"}, "councilPartySummaries": [], "allParties": null, "towns": [], "no": 205, "name": "ENEZ", "totalVote": 0, "totalVotePercent": 0, "url": "/edirne-enez-ilcesi-yerel-secim-sonuclari/"}, {"chest": {"totalChest": 22, "totalOpenChestPercent": 100, "openChest": 22, "totalVoter": 7049, "totalVote": 6069, "validVote": 5842, "invalidVote": 227, "totalJoinPercent": 86.09731876861966}, "details": [{"candidate": null, "previousTotalVote": 0, "previousTotalVotePercent": 0, "no": 9, "name": "AK Parti", "totalVote": 2285, "totalVotePercent": 39.1133173570695, "url": "/ak-parti-yerel-secim-sonuclari/"}, {"candidate": null, "previousTotalVote": 0, "previousTotalVotePercent": 0, "no": 11, "name": "MHP", "totalVote": 25, "totalVotePercent": 0.4279356384799726, "url": "/mhp-yerel-secim-sonuclari/"}, {"candidate": null, "previousTotalVote": 0, "previousTotalVotePercent": 0, "no": 21, "name": "CHP", "totalVote": 3253, "totalVotePercent": 55.682985279014034, "url": "/chp-yerel-secim-sonuclari/"}, {"candidate": null, "previousTotalVote": 0, "previousTotalVotePercent": 0, "no": 10, "name": "Yeniden Refah", "totalVote": 7, "totalVotePercent": 0.11982197877439234, "url": "/yeniden-refah-yerel-secim-sonuclari/"}, {"candidate": null, "previousTotalVote": 0, "previousTotalVotePercent": 0, "no": 87, "name": "DEM Parti", "totalVote": 0, "totalVotePercent": 0, "url": "/dem-parti-yerel-secim-sonuclari/"}, {"candidate": null, "previousTotalVote": 0, "previousTotalVotePercent": 0, "no": 0, "name": "Diğer", "totalVote": 272, "totalVotePercent": 4.655939746662102, "url": ""}], "winner": {"candidate": {"no": "0", "name": "Hüseyin Özden", "partyNo": "21", "url": "/chp/edirne/havsa/huseyin-ozden-belediye-baskani-adayi/"}, "previousTotalVote": 0, "previousTotalVotePercent": 0, "no": 21, "name": "CHP", "totalVote": 3253, "totalVotePercent": 55.682985279014034, "url": "/chp-yerel-secim-sonuclari/"}, "previousWinner": {"candidate": {"no": "0", "name": "Aydın Balkan", "partyNo": "9", "url": null}, "previousTotalVote": 0, "previousTotalVotePercent": 0, "no": 9, "name": "AK Parti", "totalVote": 3110, "totalVotePercent": 54.275741710296685, "url": "/ak-parti-yerel-secim-sonuclari/"}, "councilPartySummaries": [], "allParties": null, "towns": [], "no": 282, "name": "HAVSA", "totalVote": 0, "totalVotePercent": 0, "url": "/edirne-havsa-ilcesi-yerel-secim-sonuclari/"}, {"chest": {"totalChest": 21, "totalOpenChestPercent": 100, "openChest": 21, "totalVoter": 6356, "totalVote": 5675, "validVote": 5474, "invalidVote": 201, "totalJoinPercent": 89.28571428571429}, "details": [{"candidate": null, "previousTotalVote": 0, "previousTotalVotePercent": 0, "no": 9, "name": "AK Parti", "totalVote": 1645, "totalVotePercent": 30.051150895140665, "url": "/ak-parti-yerel-secim-sonuclari/"}, {"candidate": null, "previousTotalVote": 0, "previousTotalVotePercent": 0, "no": 11, "name": "MHP", "totalVote": 1258, "totalVotePercent": 22.981366459627328, "url": "/mhp-yerel-secim-sonuclari/"}, {"candidate": null, "previousTotalVote": 0, "previousTotalVotePercent": 0, "no": 21, "name": "CHP", "totalVote": 1533, "totalVotePercent": 28.005115089514067, "url": "/chp-yerel-secim-sonuclari/"}, {"candidate": null, "previousTotalVote": 0, "previousTotalVotePercent": 0, "no": 10, "name": "Yeniden Refah", "totalVote": 0, "totalVotePercent": 0, "url": "/yeniden-refah-yerel-secim-sonuclari/"}, {"candidate": null, "previousTotalVote": 0, "previousTotalVotePercent": 0, "no": 87, "name": "DEM Parti", "totalVote": 0, "totalVotePercent": 0, "url": "/dem-parti-yerel-secim-sonuclari/"}, {"candidate": null, "previousTotalVote": 0, "previousTotalVotePercent": 0, "no": 0, "name": "Diğer", "totalVote": 1038, "totalVotePercent": 18.96236755571794, "url": ""}], "winner": {"candidate": {"no": "0", "name": "Mehmet Kerman", "partyNo": "9", "url": "/ak-parti/edirne/ipsala/mehmet-kerman-belediye-baskani-adayi/"}, "previousTotalVote": 0, "previousTotalVotePercent": 0, "no": 9, "name": "AK Parti", "totalVote": 1645, "totalVotePercent": 30.051150895140665, "url": "/ak-parti-yerel-secim-sonuclari/"}, "previousWinner": {"candidate": {"no": "0", "name": "Abdullah Naci Ünsal", "partyNo": "22", "url": null}, "previousTotalVote": 0, "previousTotalVotePercent": 0, "no": 22, "name": "İyi Parti", "totalVote": 2545, "totalVotePercent": 48.698813624186755, "url": "/iyi-parti-yerel-secim-sonuclari/"}, "councilPartySummaries": [], "allParties": null, "towns": [{"chest": {"totalChest": 8, "totalOpenChestPercent": 100, "openChest": 8, "totalVoter": 2416, "totalVote": 2294, "validVote": 2186, "invalidVote": 108, "totalJoinPercent": 94.95033112582782}, "details": [{"candidate": null, "previousTotalVote": 0, "previousTotalVotePercent": 0, "no": 9, "name": "AK Parti", "totalVote": 781, "totalVotePercent": 35.727355901189384, "url": "/ak-parti-yerel-secim-sonuclari/"}, {"candidate": null, "previousTotalVote": 0, "previousTotalVotePercent": 0, "no": 11, "name": "MHP", "totalVote": 18, "totalVotePercent": 0.8234217749313815, "url": "/mhp-yerel-secim-sonuclari/"}, {"candidate": null, "previousTotalVote": 0, "previousTotalVotePercent": 0, "no": 21, "name": "CHP", "totalVote": 1386, "totalVotePercent": 63.403476669716376, "url": "/chp-yerel-secim-sonuclari/"}, {"candidate": null, "previousTotalVote": 0, "previousTotalVotePercent": 0, "no": 10, "name": "Yeniden Refah", "totalVote": 0, "totalVotePercent": 0, "url": "/yeniden-refah-yerel-secim-sonuclari/"}, {"candidate": null, "previousTotalVote": 0, "previousTotalVotePercent": 0, "no": 87, "name": "DEM Parti", "totalVote": 0, "totalVotePercent": 0, "url": "/dem-parti-yerel-secim-sonuclari/"}, {"candidate": null, "previousTotalVote": 0, "previousTotalVotePercent": 0, "no": 0, "name": "Diğer", "totalVote": 1, "totalVotePercent": 0.04574565416285453, "url": ""}], "winner": {"candidate": {"no": "0", "name": "Ahmet Köprü", "partyNo": "21", "url": "#"}, "previousTotalVote": 0, "previousTotalVotePercent": 0, "no": 21, "name": "CHP", "totalVote": 1386, "totalVotePercent": 63.403476669716376, "url": "/chp-yerel-secim-sonuclari/"}, "previousWinner": {"candidate": {"no": "0", "name": "Ufuk Atalay", "partyNo": "9", "url": null}, "previousTotalVote": 0, "previousTotalVotePercent": 0, "no": 9, "name": "AK Parti", "totalVote": 1210, "totalVotePercent": 55.65777368905244, "url": "/ak-parti-yerel-secim-sonuclari/"}, "no": 4850, "name": "İPSALA-YENİKARPUZLU", "totalVote": 0, "totalVotePercent": 0, "url": null}, {"chest": {"totalChest": 6, "totalOpenChestPercent": 100, "openChest": 6, "totalVoter": 1738, "totalVote": 1687, "validVote": 1579, "invalidVote": 108, "totalJoinPercent": 97.0655926352129}, "details": [{"candidate": null, "previousTotalVote": 0, "previousTotalVotePercent": 0, "no": 9, "name": "AK Parti", "totalVote": 839, "totalVotePercent": 53.134895503483214, "url": "/ak-parti-yerel-secim-sonuclari/"}, {"candidate": null, "previousTotalVote": 0, "previousTotalVotePercent": 0, "no": 11, "name": "MHP", "totalVote": 8, "totalVotePercent": 0.506649778340722, "url": "/mhp-yerel-secim-sonuclari/"}, {"candidate": null, "previousTotalVote": 0, "previousTotalVotePercent": 0, "no": 21, "name": "CHP", "totalVote": 732, "totalVotePercent": 46.35845471817606, "url": "/chp-yerel-secim-sonuclari/"}, {"candidate": null, "previousTotalVote": 0, "previousTotalVotePercent": 0, "no": 10, "name": "Yeniden Refah", "totalVote": 0, "totalVotePercent": 0, "url": "/yeniden-refah-yerel-secim-sonuclari/"}, {"candidate": null, "previousTotalVote": 0, "previousTotalVotePercent": 0, "no": 87, "name": "DEM Parti", "totalVote": 0, "totalVotePercent": 0, "url": "/dem-parti-yerel-secim-sonuclari/"}, {"candidate": null, "previousTotalVote": 0, "previousTotalVotePercent": 0, "no": 0, "name": "Diğer", "totalVote": 0, "totalVotePercent": 0, "url": ""}], "winner": {"candidate": {"no": "0", "name": "Cemal Deniz", "partyNo": "9", "url": "#"}, "previousTotalVote": 0, "previousTotalVotePercent": 0, "no": 9, "name": "AK Parti", "totalVote": 839, "totalVotePercent": 53.134895503483214, "url": "/ak-parti-yerel-secim-sonuclari/"}, "previousWinner": {"candidate": {"no": "0", "name": "Cemal Deniz", "partyNo": "9", "url": null}, "previousTotalVote": 0, "previousTotalVotePercent": 0, "no": 9, "name": "AK Parti", "totalVote": 798, "totalVotePercent": 50.12562814070352, "url": "/ak-parti-yerel-secim-sonuclari/"}, "no": 4852, "name": "İPSALA-ESETÇE", "totalVote": 0, "totalVotePercent": 0, "url": null}], "no": 309, "name": "İPSALA", "totalVote": 0, "totalVotePercent": 0, "url": "/edirne-ipsala-ilcesi-yerel-secim-sonuclari/"}, {"chest": {"totalChest": 149, "totalOpenChestPercent": 100, "openChest": 149, "totalVoter": 49031, "totalVote": 40226, "validVote": 38913, "invalidVote": 1313, "totalJoinPercent": 82.0419734453713}, "details": [{"candidate": null, "previousTotalVote": 0, "previousTotalVotePercent": 0, "no": 9, "name": "AK Parti", "totalVote": 16139, "totalVotePercent": 41.474571479968134, "url": "/ak-parti-yerel-secim-sonuclari/"}, {"candidate": null, "previousTotalVote": 0, "previousTotalVotePercent": 0, "no": 11, "name": "MHP", "totalVote": 0, "totalVotePercent": 0, "url": "/mhp-yerel-secim-sonuclari/"}, {"candidate": null, "previousTotalVote": 0, "previousTotalVotePercent": 0, "no": 21, "name": "CHP", "totalVote": 20667, "totalVotePercent": 53.110785598643126, "url": "/chp-yerel-secim-sonuclari/"}, {"candidate": null, "previousTotalVote": 0, "previousTotalVotePercent": 0, "no": 10, "name": "Yeniden Refah", "totalVote": 230, "totalVotePercent": 0.5910621129185619, "url": "/yeniden-refah-yerel-secim-sonuclari/"}, {"candidate": null, "previousTotalVote": 0, "previousTotalVotePercent": 0, "no": 87, "name": "DEM Parti", "totalVote": 380, "totalVotePercent": 0.9765374039524066, "url": "/dem-parti-yerel-secim-sonuclari/"}, {"candidate": null, "previousTotalVote": 0, "previousTotalVotePercent": 0, "no": 0, "name": "Diğer", "totalVote": 1497, "totalVotePercent": 3.8470434045177706, "url": ""}], "winner": {"candidate": {"no": "0", "name": "Mehmet Özcan", "partyNo": "21", "url": "/chp/edirne/kesan/mehmet-ozcan-belediye-baskani-adayi/"}, "previousTotalVote": 0, "previousTotalVotePercent": 0, "no": 21, "name": "CHP", "totalVote": 20667, "totalVotePercent": 53.110785598643126, "url": "/chp-yerel-secim-sonuclari/"}, "previousWinner": {"candidate": {"no": "0", "name": "Mustafa Helvacıoğlu", "partyNo": "9", "url": null}, "previousTotalVote": 0, "previousTotalVotePercent": 0, "no": 9, "name": "AK Parti", "totalVote": 18429, "totalVotePercent": 49.2477485903637, "url": "/ak-parti-yerel-secim-sonuclari/"}, "councilPartySummaries": [], "allParties": null, "towns": [{"chest": {"totalChest": 7, "totalOpenChestPercent": 100, "openChest": 7, "totalVoter": 1682, "totalVote": 1580, "validVote": 1532, "invalidVote": 48, "totalJoinPercent": 93.935790725327}, "details": [{"candidate": null, "previousTotalVote": 0, "previousTotalVotePercent": 0, "no": 9, "name": "AK Parti", "totalVote": 702, "totalVotePercent": 45.822454308093995, "url": "/ak-parti-yerel-secim-sonuclari/"}, {"candidate": null, "previousTotalVote": 0, "previousTotalVotePercent": 0, "no": 11, "name": "MHP", "totalVote": 0, "totalVotePercent": 0, "url": "/mhp-yerel-secim-sonuclari/"}, {"candidate": null, "previousTotalVote": 0, "previousTotalVotePercent": 0, "no": 21, "name": "CHP", "totalVote": 830, "totalVotePercent": 54.177545691906005, "url": "/chp-yerel-secim-sonuclari/"}, {"candidate": null, "previousTotalVote": 0, "previousTotalVotePercent": 0, "no": 10, "name": "Yeniden Refah", "totalVote": 0, "totalVotePercent": 0, "url": "/yeniden-refah-yerel-secim-sonuclari/"}, {"candidate": null, "previousTotalVote": 0, "previousTotalVotePercent": 0, "no": 87, "name": "DEM Parti", "totalVote": 0, "totalVotePercent": 0, "url": "/dem-parti-yerel-secim-sonuclari/"}, {"candidate": null, "previousTotalVote": 0, "previousTotalVotePercent": 0, "no": 0, "name": "Diğer", "totalVote": 0, "totalVotePercent": 0, "url": ""}], "winner": {"candidate": {"no": "0", "name": "Tamer Kıral", "partyNo": "21", "url": "#"}, "previousTotalVote": 0, "previousTotalVotePercent": 0, "no": 21, "name": "CHP", "totalVote": 830, "totalVotePercent": 54.177545691906005, "url": "/chp-yerel-secim-sonuclari/"}, "previousWinner": {"candidate": {"no": "0", "name": "Mustafa Türker", "partyNo": "9", "url": null}, "previousTotalVote": 0, "previousTotalVotePercent": 0, "no": 9, "name": "AK Parti", "totalVote": 833, "totalVotePercent": 53.32906530089629, "url": "/ak-parti-yerel-secim-sonuclari/"}, "no": 4854, "name": "KEŞAN-YENİMUHACİR", "totalVote": 0, "totalVotePercent": 0, "url": null}, {"chest": {"totalChest": 9, "totalOpenChestPercent": 100, "openChest": 9, "totalVoter": 2689, "totalVote": 2447, "validVote": 2355, "invalidVote": 92, "totalJoinPercent": 91.00037188545927}, "details": [{"candidate": null, "previousTotalVote": 0, "previousTotalVotePercent": 0, "no": 9, "name": "AK Parti", "totalVote": 1219, "totalVotePercent": 51.76220806794055, "url": "/ak-parti-yerel-secim-sonuclari/"}, {"candidate": null, "previousTotalVote": 0, "previousTotalVotePercent": 0, "no": 11, "name": "MHP", "totalVote": 21, "totalVotePercent": 0.89171974522293, "url": "/mhp-yerel-secim-sonuclari/"}, {"candidate": null, "previousTotalVote": 0, "previousTotalVotePercent": 0, "no": 21, "name": "CHP", "totalVote": 1114, "totalVotePercent": 47.303609341825904, "url": "/chp-yerel-secim-sonuclari/"}, {"candidate": null, "previousTotalVote": 0, "previousTotalVotePercent": 0, "no": 10, "name": "Yeniden Refah", "totalVote": 0, "totalVotePercent": 0, "url": "/yeniden-refah-yerel-secim-sonuclari/"}, {"candidate": null, "previousTotalVote": 0, "previousTotalVotePercent": 0, "no": 87, "name": "DEM Parti", "totalVote": 0, "totalVotePercent": 0, "url": "/dem-parti-yerel-secim-sonuclari/"}, {"candidate": null, "previousTotalVote": 0, "previousTotalVotePercent": 0, "no": 0, "name": "Diğer", "totalVote": 1, "totalVotePercent": 0.04246284501061571, "url": ""}], "winner": {"candidate": {"no": "0", "name": "Ferat Gülver", "partyNo": "9", "url": "#"}, "previousTotalVote": 0, "previousTotalVotePercent": 0, "no": 9, "name": "AK Parti", "totalVote": 1219, "totalVotePercent": 51.76220806794055, "url": "/ak-parti-yerel-secim-sonuclari/"}, "previousWinner": {"candidate": {"no": "0", "name": "Muhammet Örnek", "partyNo": "21", "url": null}, "previousTotalVote": 0, "previousTotalVotePercent": 0, "no": 21, "name": "CHP", "totalVote": 1486, "totalVotePercent": 51.722937695788374, "url": "/chp-yerel-secim-sonuclari/"}, "no": 4857, "name": "KEŞAN-BEĞENDİK", "totalVote": 0, "totalVotePercent": 0, "url": null}], "no": 358, "name": "KEŞAN", "totalVote": 0, "totalVotePercent": 0, "url": "/edirne-kesan-ilcesi-yerel-secim-sonuclari/"}, {"chest": {"totalChest": 4, "totalOpenChestPercent": 100, "openChest": 4, "totalVoter": 1224, "totalVote": 1121, "validVote": 1057, "invalidVote": 64, "totalJoinPercent": 91.58496732026144}, "details": [{"candidate": null, "previousTotalVote": 0, "previousTotalVotePercent": 0, "no": 9, "name": "AK Parti", "totalVote": 406, "totalVotePercent": 38.41059602649007, "url": "/ak-parti-yerel-secim-sonuclari/"}, {"candidate": null, "previousTotalVote": 0, "previousTotalVotePercent": 0, "no": 11, "name": "MHP", "totalVote": 46, "totalVotePercent": 4.351939451277199, "url": "/mhp-yerel-secim-sonuclari/"}, {"candidate": null, "previousTotalVote": 0, "previousTotalVotePercent": 0, "no": 21, "name": "CHP", "totalVote": 554, "totalVotePercent": 52.41248817407758, "url": "/chp-yerel-secim-sonuclari/"}, {"candidate": null, "previousTotalVote": 0, "previousTotalVotePercent": 0, "no": 10, "name": "Yeniden Refah", "totalVote": 5, "totalVotePercent": 0.47303689687795647, "url": "/yeniden-refah-yerel-secim-sonuclari/"}, {"candidate": null, "previousTotalVote": 0, "previousTotalVotePercent": 0, "no": 87, "name": "DEM Parti", "totalVote": 0, "totalVotePercent": 0, "url": "/dem-parti-yerel-secim-sonuclari/"}, {"candidate": null, "previousTotalVote": 0, "previousTotalVotePercent": 0, "no": 0, "name": "Diğer", "totalVote": 46, "totalVotePercent": 4.351939451277199, "url": ""}], "winner": {"candidate": {"no": "0", "name": "Zafer Sezgin Geldi", "partyNo": "21", "url": "/chp/edirne/lalapasa/zafer-sezgin-geldi-belediye-baskani-adayi/"}, "previousTotalVote": 0, "previousTotalVotePercent": 0, "no": 21, "name": "CHP", "totalVote": 554, "totalVotePercent": 52.41248817407758, "url": "/chp-yerel-secim-sonuclari/"}, "previousWinner": {"candidate": {"no": "0", "name": "İsmail Arslan", "partyNo": "9", "url": null}, "previousTotalVote": 0, "previousTotalVotePercent": 0, "no": 9, "name": "AK Parti", "totalVote": 461, "totalVotePercent": 47.67321613236815, "url": "/ak-parti-yerel-secim-sonuclari/"}, "councilPartySummaries": [], "allParties": null, "towns": [], "no": 395, "name": "LALAPAŞA", "totalVote": 0, "totalVotePercent": 0, "url": "/edirne-lalapasa-ilcesi-yerel-secim-sonuclari/"}, {"chest": {"totalChest": 8, "totalOpenChestPercent": 100, "openChest": 8, "totalVoter": 2055, "totalVote": 1753, "validVote": 1642, "invalidVote": 111, "totalJoinPercent": 85.30413625304136}, "details": [{"candidate": null, "previousTotalVote": 0, "previousTotalVotePercent": 0, "no": 9, "name": "AK Parti", "totalVote": 719, "totalVotePercent": 43.788063337393424, "url": "/ak-parti-yerel-secim-sonuclari/"}, {"candidate": null, "previousTotalVote": 0, "previousTotalVotePercent": 0, "no": 11, "name": "MHP", "totalVote": 130, "totalVotePercent": 7.917174177831912, "url": "/mhp-yerel-secim-sonuclari/"}, {"candidate": null, "previousTotalVote": 0, "previousTotalVotePercent": 0, "no": 21, "name": "CHP", "totalVote": 596, "totalVotePercent": 36.297198538367844, "url": "/chp-yerel-secim-sonuclari/"}, {"candidate": null, "previousTotalVote": 0, "previousTotalVotePercent": 0, "no": 10, "name": "Yeniden Refah", "totalVote": 7, "totalVotePercent": 0.42630937880633374, "url": "/yeniden-refah-yerel-secim-sonuclari/"}, {"candidate": null, "previousTotalVote": 0, "previousTotalVotePercent": 0, "no": 87, "name": "DEM Parti", "totalVote": 0, "totalVotePercent": 0, "url": "/dem-parti-yerel-secim-sonuclari/"}, {"candidate": null, "previousTotalVote": 0, "previousTotalVotePercent": 0, "no": 0, "name": "Diğer", "totalVote": 190, "totalVotePercent": 11.571254567600487, "url": ""}], "winner": {"candidate": {"no": "0", "name": "Yunus Atay", "partyNo": "9", "url": "/ak-parti/edirne/meric/yunus-atay-belediye-baskani-adayi/"}, "previousTotalVote": 0, "previousTotalVotePercent": 0, "no": 9, "name": "AK Parti", "totalVote": 719, "totalVotePercent": 43.788063337393424, "url": "/ak-parti-yerel-secim-sonuclari/"}, "previousWinner": {"candidate": {"no": "0", "name": "Erol Dübek", "partyNo": "21", "url": null}, "previousTotalVote": 0, "previousTotalVotePercent": 0, "no": 21, "name": "CHP", "totalVote": 1089, "totalVotePercent": 61.455981941309254, "url": "/chp-yerel-secim-sonuclari/"}, "councilPartySummaries": [], "allParties": null, "towns": [{"chest": {"totalChest": 7, "totalOpenChestPercent": 100, "openChest": 7, "totalVoter": 1994, "totalVote": 1845, "validVote": 1743, "invalidVote": 102, "totalJoinPercent": 92.52758274824474}, "details": [{"candidate": null, "previousTotalVote": 0, "previousTotalVotePercent": 0, "no": 9, "name": "AK Parti", "totalVote": 632, "totalVotePercent": 36.25932300631096, "url": "/ak-parti-yerel-secim-sonuclari/"}, {"candidate": null, "previousTotalVote": 0, "previousTotalVotePercent": 0, "no": 11, "name": "MHP", "totalVote": 215, "totalVotePercent": 12.335054503729202, "url": "/mhp-yerel-secim-sonuclari/"}, {"candidate": null, "previousTotalVote": 0, "previousTotalVotePercent": 0, "no": 21, "name": "CHP", "totalVote": 892, "totalVotePercent": 51.176133103843945, "url": "/chp-yerel-secim-sonuclari/"}, {"candidate": null, "previousTotalVote": 0, "previousTotalVotePercent": 0, "no": 10, "name": "Yeniden Refah", "totalVote": 0, "totalVotePercent": 0, "url": "/yeniden-refah-yerel-secim-sonuclari/"}, {"candidate": null, "previousTotalVote": 0, "previousTotalVotePercent": 0, "no": 87, "name": "DEM Parti", "totalVote": 0, "totalVotePercent": 0, "url": "/dem-parti-yerel-secim-sonuclari/"}, {"candidate": null, "previousTotalVote": 0, "previousTotalVotePercent": 0, "no": 0, "name": "Diğer", "totalVote": 4, "totalVotePercent": 0.22948938611589215, "url": ""}], "winner": {"candidate": {"no": "0", "name": "Gökmen Altay", "partyNo": "21", "url": "#"}, "previousTotalVote": 0, "previousTotalVotePercent": 0, "no": 21, "name": "CHP", "totalVote": 892, "totalVotePercent": 51.176133103843945, "url": "/chp-yerel-secim-sonuclari/"}, "previousWinner": {"candidate": {"no": "0", "name": "Gökmen Altay", "partyNo": "21", "url": null}, "previousTotalVote": 0, "previousTotalVotePercent": 0, "no": 21, "name": "CHP", "totalVote": 890, "totalVotePercent": 47.74678111587983, "url": "/chp-yerel-secim-sonuclari/"}, "no": 4858, "name": "MERİÇ-KÜPLÜ", "totalVote": 0, "totalVotePercent": 0, "url": null}, {"chest": {"totalChest": 5, "totalOpenChestPercent": 100, "openChest": 5, "totalVoter": 1638, "totalVote": 1528, "validVote": 1451, "invalidVote": 77, "totalJoinPercent": 93.28449328449328}, "details": [{"candidate": null, "previousTotalVote": 0, "previousTotalVotePercent": 0, "no": 9, "name": "AK Parti", "totalVote": 622, "totalVotePercent": 42.866988283942106, "url": "/ak-parti-yerel-secim-sonuclari/"}, {"candidate": null, "previousTotalVote": 0, "previousTotalVotePercent": 0, "no": 11, "name": "MHP", "totalVote": 0, "totalVotePercent": 0, "url": "/mhp-yerel-secim-sonuclari/"}, {"candidate": null, "previousTotalVote": 0, "previousTotalVotePercent": 0, "no": 21, "name": "CHP", "totalVote": 403, "totalVotePercent": 27.77394900068918, "url": "/chp-yerel-secim-sonuclari/"}, {"candidate": null, "previousTotalVote": 0, "previousTotalVotePercent": 0, "no": 10, "name": "Yeniden Refah", "totalVote": 0, "totalVotePercent": 0, "url": "/yeniden-refah-yerel-secim-sonuclari/"}, {"candidate": null, "previousTotalVote": 0, "previousTotalVotePercent": 0, "no": 87, "name": "DEM Parti", "totalVote": 0, "totalVotePercent": 0, "url": "/dem-parti-yerel-secim-sonuclari/"}, {"candidate": null, "previousTotalVote": 0, "previousTotalVotePercent": 0, "no": 0, "name": "Diğer", "totalVote": 426, "totalVotePercent": 29.35906271536871, "url": ""}], "winner": {"candidate": {"no": "0", "name": "Göksel Tüfekçi", "partyNo": "9", "url": "#"}, "previousTotalVote": 0, "previousTotalVotePercent": 0, "no": 9, "name": "AK Parti", "totalVote": 622, "totalVotePercent": 42.866988283942106, "url": "/ak-parti-yerel-secim-sonuclari/"}, "previousWinner": {"candidate": {"no": "0", "name": "Hasan Çatalkaya", "partyNo": "9", "url": null}, "previousTotalVote": 0, "previousTotalVotePercent": 0, "no": 9, "name": "AK Parti", "totalVote": 632, "totalVotePercent": 42.473118279569896, "url": "/ak-parti-yerel-secim-sonuclari/"}, "no": 4859, "name": "MERİÇ-SUBAŞI", "totalVote": 0, "totalVotePercent": 0, "url": null}], "no": 416, "name": "MERİÇ", "totalVote": 0, "totalVotePercent": 0, "url": "/edirne-meric-ilcesi-yerel-secim-sonuclari/"}, {"chest": {"totalChest": 389, "totalOpenChestPercent": 100, "openChest": 389, "totalVoter": 129084, "totalVote": 102127, "validVote": 99116, "invalidVote": 3011, "totalJoinPercent": 79.11669920361935}, "details": [{"candidate": null, "previousTotalVote": 0, "previousTotalVotePercent": 0, "no": 9, "name": "AK Parti", "totalVote": 42119, "totalVotePercent": 42.49465273013439, "url": "/ak-parti-yerel-secim-sonuclari/"}, {"candidate": null, "previousTotalVote": 0, "previousTotalVotePercent": 0, "no": 11, "name": "MHP", "totalVote": 0, "totalVotePercent": 0, "url": "/mhp-yerel-secim-sonuclari/"}, {"candidate": null, "previousTotalVote": 0, "previousTotalVotePercent": 0, "no": 21, "name": "CHP", "totalVote": 46260, "totalVotePercent": 46.67258565720974, "url": "/chp-yerel-secim-sonuclari/"}, {"candidate": null, "previousTotalVote": 0, "previousTotalVotePercent": 0, "no": 10, "name": "Yeniden Refah", "totalVote": 337, "totalVotePercent": 0.3400056499455184, "url": "/yeniden-refah-yerel-secim-sonuclari/"}, {"candidate": null, "previousTotalVote": 0, "previousTotalVotePercent": 0, "no": 87, "name": "DEM Parti", "totalVote": 987, "totalVotePercent": 0.9958028976149158, "url": "/dem-parti-yerel-secim-sonuclari/"}, {"candidate": null, "previousTotalVote": 0, "previousTotalVotePercent": 0, "no": 0, "name": "Diğer", "totalVote": 9413, "totalVotePercent": 9.496953065095443, "url": ""}], "winner": {"candidate": {"no": "0", "name": "Filiz Gencan Akın", "partyNo": "21", "url": "/chp/edirne/merkez/filiz-gencan-akin-belediye-baskani-adayi/"}, "previousTotalVote": 0, "previousTotalVotePercent": 0, "no": 21, "name": "CHP", "totalVote": 46260, "totalVotePercent": 46.67258565720974, "url": "/chp-yerel-secim-sonuclari/"}, "previousWinner": {"candidate": {"no": "0", "name": "Recep Gürkan", "partyNo": "21", "url": null}, "previousTotalVote": 0, "previousTotalVotePercent": 0, "no": 21, "name": "CHP", "totalVote": 42388, "totalVotePercent": 44.86879571508717, "url": "/chp-yerel-secim-sonuclari/"}, "councilPartySummaries": [], "allParties": null, "towns": [], "no": 193, "name": "MERKEZ", "totalVote": 0, "totalVotePercent": 0, "url": "/edirne-merkez-ilcesi-yerel-secim-sonuclari/"}, {"chest": {"totalChest": 7, "totalOpenChestPercent": 100, "openChest": 7, "totalVoter": 2206, "totalVote": 1793, "validVote": 1724, "invalidVote": 69, "totalJoinPercent": 81.27833182230282}, "details": [{"candidate": null, "previousTotalVote": 0, "previousTotalVotePercent": 0, "no": 9, "name": "AK Parti", "totalVote": 0, "totalVotePercent": 0, "url": "/ak-parti-yerel-secim-sonuclari/"}, {"candidate": null, "previousTotalVote": 0, "previousTotalVotePercent": 0, "no": 11, "name": "MHP", "totalVote": 472, "totalVotePercent": 27.378190255220417, "url": "/mhp-yerel-secim-sonuclari/"}, {"candidate": null, "previousTotalVote": 0, "previousTotalVotePercent": 0, "no": 21, "name": "CHP", "totalVote": 1080, "totalVotePercent": 62.64501160092807, "url": "/chp-yerel-secim-sonuclari/"}, {"candidate": null, "previousTotalVote": 0, "previousTotalVotePercent": 0, "no": 10, "name": "Yeniden Refah", "totalVote": 0, "totalVotePercent": 0, "url": "/yeniden-refah-yerel-secim-sonuclari/"}, {"candidate": null, "previousTotalVote": 0, "previousTotalVotePercent": 0, "no": 87, "name": "DEM Parti", "totalVote": 0, "totalVotePercent": 0, "url": "/dem-parti-yerel-secim-sonuclari/"}, {"candidate": null, "previousTotalVote": 0, "previousTotalVotePercent": 0, "no": 0, "name": "Diğer", "totalVote": 172, "totalVotePercent": 9.976798143851509, "url": ""}], "winner": {"candidate": {"no": "0", "name": "Mehmet Ormankıran", "partyNo": "21", "url": "/chp/edirne/suloglu/mehmet-ormankiran-belediye-baskani-adayi/"}, "previousTotalVote": 0, "previousTotalVotePercent": 0, "no": 21, "name": "CHP", "totalVote": 1080, "totalVotePercent": 62.64501160092807, "url": "/chp-yerel-secim-sonuclari/"}, "previousWinner": {"candidate": {"no": "0", "name": "Mehmet Ormankıran", "partyNo": "21", "url": null}, "previousTotalVote": 0, "previousTotalVotePercent": 0, "no": 21, "name": "CHP", "totalVote": 930, "totalVotePercent": 55.39011316259678, "url": "/chp-yerel-secim-sonuclari/"}, "councilPartySummaries": [], "allParties": null, "towns": [], "no": 881, "name": "SÜLOĞLU", "totalVote": 0, "totalVotePercent": 0, "url": "/edirne-suloglu-ilcesi-yerel-secim-sonuclari/"}, {"chest": {"totalChest": 96, "totalOpenChestPercent": 100, "openChest": 96, "totalVoter": 30978, "totalVote": 25122, "validVote": 24153, "invalidVote": 969, "totalJoinPercent": 81.0962618632578}, "details": [{"candidate": null, "previousTotalVote": 0, "previousTotalVotePercent": 0, "no": 9, "name": "AK Parti", "totalVote": 7677, "totalVotePercent": 31.78487144454105, "url": "/ak-parti-yerel-secim-sonuclari/"}, {"candidate": null, "previousTotalVote": 0, "previousTotalVotePercent": 0, "no": 11, "name": "MHP", "totalVote": 169, "totalVotePercent": 0.6997060406574752, "url": "/mhp-yerel-secim-sonuclari/"}, {"candidate": null, "previousTotalVote": 0, "previousTotalVotePercent": 0, "no": 21, "name": "CHP", "totalVote": 7941, "totalVotePercent": 32.87790336604149, "url": "/chp-yerel-secim-sonuclari/"}, {"candidate": null, "previousTotalVote": 0, "previousTotalVotePercent": 0, "no": 10, "name": "Yeniden Refah", "totalVote": 0, "totalVotePercent": 0, "url": "/yeniden-refah-yerel-secim-sonuclari/"}, {"candidate": null, "previousTotalVote": 0, "previousTotalVotePercent": 0, "no": 87, "name": "DEM Parti", "totalVote": 0, "totalVotePercent": 0, "url": "/dem-parti-yerel-secim-sonuclari/"}, {"candidate": null, "previousTotalVote": 0, "previousTotalVotePercent": 0, "no": 0, "name": "Diğer", "totalVote": 8366, "totalVotePercent": 34.637519148759985, "url": ""}], "winner": {"candidate": {"no": "0", "name": "Ediz Martin", "partyNo": "22", "url": "/iyi-parti/edirne/uzunkopru/ediz-martin-belediye-baskani-adayi/"}, "previousTotalVote": 0, "previousTotalVotePercent": 0, "no": 22, "name": "İYİ Parti", "totalVote": 8026, "totalVotePercent": 33.229826522585185, "url": "/iyi-parti-yerel-secim-sonuclari/"}, "previousWinner": {"candidate": {"no": "0", "name": "Özlem Becan", "partyNo": "21", "url": null}, "previousTotalVote": 0, "previousTotalVotePercent": 0, "no": 21, "name": "CHP", "totalVote": 13759, "totalVotePercent": 56.47498255551451, "url": "/chp-yerel-secim-sonuclari/"}, "councilPartySummaries": [], "allParties": null, "towns": [{"chest": {"totalChest": 8, "totalOpenChestPercent": 100, "openChest": 8, "totalVoter": 2254, "totalVote": 2109, "validVote": 1978, "invalidVote": 131, "totalJoinPercent": 93.56699201419698}, "details": [{"candidate": null, "previousTotalVote": 0, "previousTotalVotePercent": 0, "no": 9, "name": "AK Parti", "totalVote": 1036, "totalVotePercent": 52.376137512639026, "url": "/ak-parti-yerel-secim-sonuclari/"}, {"candidate": null, "previousTotalVote": 0, "previousTotalVotePercent": 0, "no": 11, "name": "MHP", "totalVote": 23, "totalVotePercent": 1.1627906976744187, "url": "/mhp-yerel-secim-sonuclari/"}, {"candidate": null, "previousTotalVote": 0, "previousTotalVotePercent": 0, "no": 21, "name": "CHP", "totalVote": 899, "totalVotePercent": 45.44994944388271, "url": "/chp-yerel-secim-sonuclari/"}, {"candidate": null, "previousTotalVote": 0, "previousTotalVotePercent": 0, "no": 10, "name": "Yeniden Refah", "totalVote": 0, "totalVotePercent": 0, "url": "/yeniden-refah-yerel-secim-sonuclari/"}, {"candidate": null, "previousTotalVote": 0, "previousTotalVotePercent": 0, "no": 87, "name": "DEM Parti", "totalVote": 0, "totalVotePercent": 0, "url": "/dem-parti-yerel-secim-sonuclari/"}, {"candidate": null, "previousTotalVote": 0, "previousTotalVotePercent": 0, "no": 0, "name": "Diğer", "totalVote": 20, "totalVotePercent": 1.0111223458038423, "url": ""}], "winner": {"candidate": {"no": "0", "name": "Samet Ertaş", "partyNo": "9", "url": "#"}, "previousTotalVote": 0, "previousTotalVotePercent": 0, "no": 9, "name": "AK Parti", "totalVote": 1036, "totalVotePercent": 52.376137512639026, "url": "/ak-parti-yerel-secim-sonuclari/"}, "previousWinner": {"candidate": {"no": "0", "name": "Hüseyin Tütüncü", "partyNo": "21", "url": null}, "previousTotalVote": 0, "previousTotalVotePercent": 0, "no": 21, "name": "CHP", "totalVote": 1132, "totalVotePercent": 51.106094808126414, "url": "/chp-yerel-secim-sonuclari/"}, "no": 4862, "name": "UZUNKÖPRÜ-KIRCASALİH", "totalVote": 0, "totalVotePercent": 0, "url": null}], "no": 598, "name": "UZUNKÖPRÜ", "totalVote": 0, "totalVotePercent": 0, "url": "/edirne-uzunkopru-ilcesi-yerel-secim-sonuclari/"}], "partySummaries": [{"candidate": {"no": "0", "name": "Filiz Gencan Akın", "partyNo": "21", "url": "/chp/edirne/merkez/filiz-gencan-akin-belediye-baskani-adayi/"}, "previousTotalVote": null, "previousTotalVotePercent": null, "no": 21, "name": "CHP", "totalVote": 46260, "totalVotePercent": 46.67258565720974, "url": "/chp-yerel-secim-sonuclari/"}, {"candidate": {"no": "0", "name": "Belgin İba", "partyNo": "9", "url": "/ak-parti/edirne/merkez/belgin-iba-belediye-baskani-adayi/"}, "previousTotalVote": null, "previousTotalVotePercent": null, "no": 9, "name": "AK Parti", "totalVote": 42119, "totalVotePercent": 42.49465273013439, "url": "/ak-parti-yerel-secim-sonuclari/"}, {"candidate": {"no": "0", "name": "Hamdi Sedefçi", "partyNo": "22", "url": "/iyi-parti/edirne/merkez/hamdi-sedefci-belediye-baskani-adayi/"}, "previousTotalVote": null, "previousTotalVotePercent": null, "no": 22, "name": "İYİ Parti", "totalVote": 5391, "totalVotePercent": 5.439081480285726, "url": "/iyi-parti-yerel-secim-sonuclari/"}, {"candidate": {"no": "0", "name": "Serkan Konak", "partyNo": "24", "url": "#"}, "previousTotalVote": null, "previousTotalVotePercent": null, "no": 24, "name": "Zafer Partisi", "totalVote": 1920, "totalVotePercent": 1.9371241777311432, "url": "/zafer-partisi-yerel-secim-sonuclari/"}, {"candidate": {"no": "0", "name": "Aylin Hacaloğlu", "partyNo": "87", "url": "#"}, "previousTotalVote": null, "previousTotalVotePercent": null, "no": 87, "name": "DEM Parti", "totalVote": 987, "totalVotePercent": 0.9958028976149158, "url": "/dem-parti-yerel-secim-sonuclari/"}, {"candidate": {"no": "0", "name": "Ali Yalçındağ", "partyNo": "10", "url": "#"}, "previousTotalVote": null, "previousTotalVotePercent": null, "no": 10, "name": "Yeniden Refah", "totalVote": 337, "totalVotePercent": 0.3400056499455184, "url": "/yeniden-refah-yerel-secim-sonuclari/"}, {"candidate": {"no": "0", "name": "Tezcan Karakütük", "partyNo": "34", "url": "#"}, "previousTotalVote": null, "previousTotalVotePercent": null, "no": 34, "name": "Saadet", "totalVote": 326, "totalVotePercent": 0.328907542677267, "url": "/saadet-yerel-secim-sonuclari/"}, {"candidate": {"no": "0", "name": "Çiğdem Bora", "partyNo": "7", "url": "#"}, "previousTotalVote": null, "previousTotalVotePercent": null, "no": 7, "name": "Memleket", "totalVote": 245, "totalVotePercent": 0.24718511642923444, "url": "/memleket-yerel-secim-sonuclari/"}, {"candidate": {"no": "0", "name": "Hava Aksoy", "partyNo": "31", "url": "#"}, "previousTotalVote": null, "previousTotalVotePercent": null, "no": 31, "name": "Gelecek Partisi", "totalVote": 235, "totalVotePercent": 0.2370959280035514, "url": "/gelecek-partisi-yerel-secim-sonuclari/"}, {"candidate": {"no": "0", "name": "Emre Gebeş", "partyNo": "3", "url": "#"}, "previousTotalVote": null, "previousTotalVotePercent": null, "no": 3, "name": "TKP", "totalVote": 220, "totalVotePercent": 0.22196214536502684, "url": "/tkp-yerel-secim-sonuclari/"}, {"candidate": {"no": "0", "name": "Çetin Atla", "partyNo": "29", "url": "#"}, "previousTotalVote": null, "previousTotalVotePercent": null, "no": 29, "name": "DSP", "totalVote": 148, "totalVotePercent": 0.14931998870010896, "url": "/dsp-yerel-secim-sonuclari/"}, {"candidate": {"no": "0", "name": "Tolga Zülka", "partyNo": "33", "url": "#"}, "previousTotalVote": null, "previousTotalVotePercent": null, "no": 33, "name": "HÜDA PAR", "totalVote": 142, "totalVotePercent": 0.14326647564469913, "url": "/huda-par-yerel-secim-sonuclari/"}, {"candidate": {"no": "0", "name": "Arif Köroğlu", "partyNo": "18", "url": "#"}, "previousTotalVote": null, "previousTotalVotePercent": null, "no": 18, "name": "Milli Yol", "totalVote": 115, "totalVotePercent": 0.11602566689535494, "url": "/milli-yol-yerel-secim-sonuclari/"}, {"candidate": {"no": "2024214", "name": "Songül Çetinkaya Tül", "partyNo": "0", "url": "#"}, "previousTotalVote": null, "previousTotalVotePercent": null, "no": 0, "name": "Bağımsız", "totalVote": 104, "totalVotePercent": 0.1049275596271036, "url": ""}, {"candidate": {"no": "0", "name": "Cem Özcan", "partyNo": "25", "url": "#"}, "previousTotalVote": null, "previousTotalVotePercent": null, "no": 25, "name": "BTP", "totalVote": 103, "totalVotePercent": 0.10391864078453529, "url": "/btp-yerel-secim-sonuclari/"}, {"candidate": {"no": "0", "name": "Nail Gün", "partyNo": "8", "url": "#"}, "previousTotalVote": null, "previousTotalVotePercent": null, "no": 8, "name": "Büyük Birlik", "totalVote": 96, "totalVotePercent": 0.09685620888655716, "url": "/buyuk-birlik-yerel-secim-sonuclari/"}, {"candidate": {"no": "0", "name": "Fatma Müzeyyen Oktay", "partyNo": "19", "url": "#"}, "previousTotalVote": null, "previousTotalVotePercent": null, "no": 19, "name": "Vatan", "totalVote": 88, "totalVotePercent": 0.08878485814601074, "url": "/vatan-yerel-secim-sonuclari/"}, {"candidate": {"no": "0", "name": "Ayla Şahbaz", "partyNo": "17", "url": "#"}, "previousTotalVote": null, "previousTotalVotePercent": null, "no": 17, "name": "HKP", "totalVote": 77, "totalVotePercent": 0.07768675087775939, "url": "/hkp-yerel-secim-sonuclari/"}, {"candidate": {"no": "0", "name": "Hanım Hülya Göçer", "partyNo": "27", "url": "#"}, "previousTotalVote": null, "previousTotalVotePercent": null, "no": 27, "name": "DEVA Partisi", "totalVote": 71, "totalVotePercent": 0.07163323782234957, "url": "/deva-partisi-yerel-secim-sonuclari/"}, {"candidate": {"no": "0", "name": "Hikmet Sofu", "partyNo": "1", "url": "#"}, "previousTotalVote": null, "previousTotalVotePercent": null, "no": 1, "name": "Millet", "totalVote": 36, "totalVotePercent": 0.036321078332458935, "url": "/millet-yerel-secim-sonuclari/"}, {"candidate": {"no": "0", "name": "Gökdeniz Altuntaş", "partyNo": "4", "url": "#"}, "previousTotalVote": null, "previousTotalVotePercent": null, "no": 4, "name": "TKH", "totalVote": 35, "totalVotePercent": 0.03531215948989063, "url": "/tkh-yerel-secim-sonuclari/"}, {"candidate": {"no": "0", "name": "Sabri Serin", "partyNo": "2", "url": "#"}, "previousTotalVote": null, "previousTotalVotePercent": null, "no": 2, "name": "HAK-PAR", "totalVote": 34, "totalVotePercent": 0.034303240647322326, "url": "/hak-par-yerel-secim-sonuclari/"}, {"candidate": {"no": "0", "name": "Cemil Murat Dodanlı", "partyNo": "88", "url": "#"}, "previousTotalVote": null, "previousTotalVotePercent": null, "no": 88, "name": "AB Parti", "totalVote": 27, "totalVotePercent": 0.027240808749344203, "url": "/ab-parti-yerel-secim-sonuclari/"}], "councilPartySummaries": [{"previousTotalVote": 112789, "previousTotalVotePercent": 43.18092197196795, "candidate": null, "previousCandidate": null, "no": 21, "name": "CHP", "totalVote": 124735, "totalVotePercent": 48.1587441314554, "url": "/chp-yerel-secim-sonuclari/"}, {"previousTotalVote": 91843, "previousTotalVotePercent": 35.16181025340638, "candidate": null, "previousCandidate": null, "no": 9, "name": "AK Parti", "totalVote": 84179, "totalVotePercent": 32.500540523844826, "url": "/ak-parti-yerel-secim-sonuclari/"}, {"previousTotalVote": 25838, "previousTotalVotePercent": 9.891998882086975, "candidate": null, "previousCandidate": null, "no": 22, "name": "İYİ Parti", "totalVote": 21872, "totalVotePercent": 8.444526809982703, "url": "/iyi-parti-yerel-secim-sonuclari/"}, {"previousTotalVote": 14765, "previousTotalVotePercent": 5.65273486701812, "candidate": null, "previousCandidate": null, "no": 11, "name": "MHP", "totalVote": 11427, "totalVotePercent": 4.411832839140104, "url": "/mhp-yerel-secim-sonuclari/"}, {"previousTotalVote": null, "previousTotalVotePercent": null, "candidate": null, "previousCandidate": null, "no": 24, "name": "Zafer Partisi", "totalVote": 5030, "totalVotePercent": 1.9420249567580925, "url": "/zafer-partisi-yerel-secim-sonuclari/"}, {"previousTotalVote": null, "previousTotalVotePercent": null, "candidate": null, "previousCandidate": null, "no": 13, "name": "TİP", "totalVote": 3005, "totalVotePercent": 1.1601958240672103, "url": "/tip-yerel-secim-sonuclari/"}, {"previousTotalVote": 4046, "previousTotalVotePercent": 1.5489986638642272, "candidate": null, "previousCandidate": null, "no": 34, "name": "Saadet", "totalVote": 1660, "totalVotePercent": 0.6409068445762293, "url": "/saadet-yerel-secim-sonuclari/"}, {"previousTotalVote": null, "previousTotalVotePercent": null, "candidate": null, "previousCandidate": null, "no": 10, "name": "Yeniden Refah", "totalVote": 1432, "totalVotePercent": 0.5528786755621448, "url": "/yeniden-refah-yerel-secim-sonuclari/"}, {"previousTotalVote": null, "previousTotalVotePercent": null, "candidate": null, "previousCandidate": null, "no": 5, "name": "Sol Parti", "totalVote": 961, "totalVotePercent": 0.3710310106251544, "url": "/sol-parti-yerel-secim-sonuclari/"}, {"previousTotalVote": 6025, "previousTotalVotePercent": 2.306652731038549, "candidate": null, "previousCandidate": null, "no": 25, "name": "BTP", "totalVote": 666, "totalVotePercent": 0.2571349147516679, "url": "/btp-yerel-secim-sonuclari/"}, {"previousTotalVote": null, "previousTotalVotePercent": null, "candidate": null, "previousCandidate": null, "no": 7, "name": "Memleket", "totalVote": 630, "totalVotePercent": 0.24323573017049666, "url": "/memleket-yerel-secim-sonuclari/"}, {"previousTotalVote": 1907, "previousTotalVotePercent": 0.7300890884797532, "candidate": null, "previousCandidate": null, "no": 28, "name": "DP", "totalVote": 629, "totalVotePercent": 0.24284964170990858, "url": "/dp-yerel-secim-sonuclari/"}, {"previousTotalVote": null, "previousTotalVotePercent": null, "candidate": null, "previousCandidate": null, "no": 87, "name": "DEM Parti", "totalVote": 608, "totalVotePercent": 0.2347417840375587, "url": "/dem-parti-yerel-secim-sonuclari/"}, {"previousTotalVote": null, "previousTotalVotePercent": null, "candidate": null, "previousCandidate": null, "no": 33, "name": "HÜDA PAR", "totalVote": 461, "totalVotePercent": 0.17798678033110946, "url": "/huda-par-yerel-secim-sonuclari/"}, {"previousTotalVote": null, "previousTotalVotePercent": null, "candidate": null, "previousCandidate": null, "no": 31, "name": "Gelecek Partisi", "totalVote": 419, "totalVotePercent": 0.1617710649864097, "url": "/gelecek-partisi-yerel-secim-sonuclari/"}, {"previousTotalVote": 1139, "previousTotalVotePercent": 0.43606264907102193, "candidate": null, "previousCandidate": null, "no": 8, "name": "Büyük Birlik", "totalVote": 329, "totalVotePercent": 0.1270231035334816, "url": "/buyuk-birlik-yerel-secim-sonuclari/"}, {"previousTotalVote": null, "previousTotalVotePercent": null, "candidate": null, "previousCandidate": null, "no": 29, "name": "DSP", "totalVote": 294, "totalVotePercent": 0.11351000741289845, "url": "/dsp-yerel-secim-sonuclari/"}, {"previousTotalVote": null, "previousTotalVotePercent": null, "candidate": null, "previousCandidate": null, "no": 18, "name": "Milli Yol", "totalVote": 268, "totalVotePercent": 0.1034717074376081, "url": "/milli-yol-yerel-secim-sonuclari/"}, {"previousTotalVote": 531, "previousTotalVotePercent": 0.20329171787244307, "candidate": null, "previousCandidate": null, "no": 19, "name": "Vatan", "totalVote": 248, "totalVotePercent": 0.0957499382258463, "url": "/vatan-yerel-secim-sonuclari/"}, {"previousTotalVote": null, "previousTotalVotePercent": null, "candidate": null, "previousCandidate": null, "no": 1, "name": "Millet", "totalVote": 155, "totalVotePercent": 0.05984371139115394, "url": "/millet-yerel-secim-sonuclari/"}], "councilPartyMap": [{"chest": {"totalChest": 12, "totalOpenChestPercent": 100, "openChest": 12, "totalVoter": 3581, "totalVote": 3092, "validVote": 2979, "invalidVote": 113, "totalJoinPercent": 86.34459648142978}, "details": [{"candidate": {"no": "0", "name": "Özkan Günenç", "partyNo": "21", "url": "/chp/edirne/enez/ozkan-gunenc-belediye-baskani-adayi/"}, "previousTotalVote": null, "previousTotalVotePercent": null, "no": 21, "name": "CHP", "totalVote": 1481, "totalVotePercent": 49.71466935213159, "url": "/chp-yerel-secim-sonuclari/"}, {"candidate": {"no": "0", "name": "Abdullah Bostancı", "partyNo": "9", "url": "/ak-parti/edirne/enez/abdullah-bostanci-belediye-baskani-adayi/"}, "previousTotalVote": null, "previousTotalVotePercent": null, "no": 9, "name": "AK Parti", "totalVote": 1045, "totalVotePercent": 35.07888553205774, "url": "/ak-parti-yerel-secim-sonuclari/"}], "winner": {"candidate": {"no": "0", "name": "Özkan Günenç", "partyNo": "21", "url": "/chp/edirne/enez/ozkan-gunenc-belediye-baskani-adayi/"}, "previousTotalVote": null, "previousTotalVotePercent": null, "no": 21, "name": "CHP", "totalVote": 1481, "totalVotePercent": 49.71466935213159, "url": "/chp-yerel-secim-sonuclari/"}, "previousWinner": null, "councilPartySummaries": [], "allParties": null, "towns": [], "no": 205, "name": "ENEZ", "totalVote": 0, "totalVotePercent": 0, "url": "/edirne-enez-ilcesi-yerel-secim-sonuclari/"}, {"chest": {"totalChest": 22, "totalOpenChestPercent": 100, "openChest": 22, "totalVoter": 7049, "totalVote": 6067, "validVote": 5804, "invalidVote": 263, "totalJoinPercent": 86.06894594978012}, "details": [{"candidate": {"no": "0", "name": "Hüseyin Özden", "partyNo": "21", "url": "/chp/edirne/havsa/huseyin-ozden-belediye-baskani-adayi/"}, "previousTotalVote": null, "previousTotalVotePercent": null, "no": 21, "name": "CHP", "totalVote": 3154, "totalVotePercent": 54.34183321847002, "url": "/chp-yerel-secim-sonuclari/"}, {"candidate": {"no": "0", "name": "Aydın Balkan", "partyNo": "9", "url": "/ak-parti/edirne/havsa/aydin-balkan-belediye-baskani-adayi/"}, "previousTotalVote": null, "previousTotalVotePercent": null, "no": 9, "name": "AK Parti", "totalVote": 1974, "totalVotePercent": 34.01102687801516, "url": "/ak-parti-yerel-secim-sonuclari/"}], "winner": {"candidate": {"no": "0", "name": "Hüseyin Özden", "partyNo": "21", "url": "/chp/edirne/havsa/huseyin-ozden-belediye-baskani-adayi/"}, "previousTotalVote": null, "previousTotalVotePercent": null, "no": 21, "name": "CHP", "totalVote": 3154, "totalVotePercent": 54.34183321847002, "url": "/chp-yerel-secim-sonuclari/"}, "previousWinner": null, "councilPartySummaries": [], "allParties": null, "towns": [], "no": 282, "name": "HAVSA", "totalVote": 0, "totalVotePercent": 0, "url": "/edirne-havsa-ilcesi-yerel-secim-sonuclari/"}, {"chest": {"totalChest": 21, "totalOpenChestPercent": 100, "openChest": 21, "totalVoter": 6356, "totalVote": 5675, "validVote": 5395, "invalidVote": 280, "totalJoinPercent": 89.28571428571429}, "details": [{"candidate": {"no": "0", "name": "Cenan Tetik", "partyNo": "21", "url": "/chp/edirne/ipsala/cenan-tetik-belediye-baskani-adayi/"}, "previousTotalVote": null, "previousTotalVotePercent": null, "no": 21, "name": "CHP", "totalVote": 1626, "totalVotePercent": 30.139017608897127, "url": "/chp-yerel-secim-sonuclari/"}, {"candidate": {"no": "0", "name": "Mehmet Kerman", "partyNo": "9", "url": "/ak-parti/edirne/ipsala/mehmet-kerman-belediye-baskani-adayi/"}, "previousTotalVote": null, "previousTotalVotePercent": null, "no": 9, "name": "AK Parti", "totalVote": 1541, "totalVotePercent": 28.563484708063022, "url": "/ak-parti-yerel-secim-sonuclari/"}], "winner": {"candidate": {"no": "0", "name": "Cenan Tetik", "partyNo": "21", "url": "/chp/edirne/ipsala/cenan-tetik-belediye-baskani-adayi/"}, "previousTotalVote": null, "previousTotalVotePercent": null, "no": 21, "name": "CHP", "totalVote": 1626, "totalVotePercent": 30.139017608897127, "url": "/chp-yerel-secim-sonuclari/"}, "previousWinner": null, "councilPartySummaries": [], "allParties": null, "towns": [], "no": 309, "name": "İPSALA", "totalVote": 0, "totalVotePercent": 0, "url": "/edirne-ipsala-ilcesi-yerel-secim-sonuclari/"}, {"chest": {"totalChest": 6, "totalOpenChestPercent": 100, "openChest": 6, "totalVoter": 1738, "totalVote": 1686, "validVote": 1590, "invalidVote": 96, "totalJoinPercent": 97.00805523590334}, "details": [{"candidate": null, "previousTotalVote": null, "previousTotalVotePercent": null, "no": 9, "name": "AK Parti", "totalVote": 835, "totalVotePercent": 52.515723270440255, "url": "/ak-parti-yerel-secim-sonuclari/"}, {"candidate": null, "previousTotalVote": null, "previousTotalVotePercent": null, "no": 21, "name": "CHP", "totalVote": 743, "totalVotePercent": 46.729559748427675, "url": "/chp-yerel-secim-sonuclari/"}], "winner": {"candidate": null, "previousTotalVote": null, "previousTotalVotePercent": null, "no": 9, "name": "AK Parti", "totalVote": 835, "totalVotePercent": 52.515723270440255, "url": "/ak-parti-yerel-secim-sonuclari/"}, "previousWinner": null, "councilPartySummaries": [], "allParties": null, "towns": [], "no": 4852, "name": "İPSALA-ESETÇE", "totalVote": 0, "totalVotePercent": 0, "url": "/edirne-ipsala-esetce-ilcesi-yerel-secim-sonuclari/"}, {"chest": {"totalChest": 8, "totalOpenChestPercent": 100, "openChest": 8, "totalVoter": 2416, "totalVote": 2293, "validVote": 2185, "invalidVote": 108, "totalJoinPercent": 94.90894039735099}, "details": [{"candidate": null, "previousTotalVote": null, "previousTotalVotePercent": null, "no": 21, "name": "CHP", "totalVote": 1367, "totalVotePercent": 62.5629290617849, "url": "/chp-yerel-secim-sonuclari/"}, {"candidate": null, "previousTotalVote": null, "previousTotalVotePercent": null, "no": 9, "name": "AK Parti", "totalVote": 781, "totalVotePercent": 35.74370709382151, "url": "/ak-parti-yerel-secim-sonuclari/"}], "winner": {"candidate": null, "previousTotalVote": null, "previousTotalVotePercent": null, "no": 21, "name": "CHP", "totalVote": 1367, "totalVotePercent": 62.5629290617849, "url": "/chp-yerel-secim-sonuclari/"}, "previousWinner": null, "councilPartySummaries": [], "allParties": null, "towns": [], "no": 4850, "name": "İPSALA-YENİKARPUZLU", "totalVote": 0, "totalVotePercent": 0, "url": "/edirne-ipsala-yenikarpuzlu-ilcesi-yerel-secim-sonuclari/"}, {"chest": {"totalChest": 149, "totalOpenChestPercent": 100, "openChest": 149, "totalVoter": 49031, "totalVote": 40240, "validVote": 38789, "invalidVote": 1451, "totalJoinPercent": 82.07052680956946}, "details": [{"candidate": {"no": "0", "name": "Mehmet Özcan", "partyNo": "21", "url": "/chp/edirne/kesan/mehmet-ozcan-belediye-baskani-adayi/"}, "previousTotalVote": null, "previousTotalVotePercent": null, "no": 21, "name": "CHP", "totalVote": 21270, "totalVotePercent": 54.8351336719173, "url": "/chp-yerel-secim-sonuclari/"}, {"candidate": {"no": "0", "name": "Mustafa Helvacıoğlu", "partyNo": "9", "url": "/ak-parti/edirne/kesan/mustafa-helvacioglu-belediye-baskani-adayi/"}, "previousTotalVote": null, "previousTotalVotePercent": null, "no": 9, "name": "AK Parti", "totalVote": 14003, "totalVotePercent": 36.10044084663178, "url": "/ak-parti-yerel-secim-sonuclari/"}], "winner": {"candidate": {"no": "0", "name": "Mehmet Özcan", "partyNo": "21", "url": "/chp/edirne/kesan/mehmet-ozcan-belediye-baskani-adayi/"}, "previousTotalVote": null, "previousTotalVotePercent": null, "no": 21, "name": "CHP", "totalVote": 21270, "totalVotePercent": 54.8351336719173, "url": "/chp-yerel-secim-sonuclari/"}, "previousWinner": null, "councilPartySummaries": [], "allParties": null, "towns": [], "no": 358, "name": "KEŞAN", "totalVote": 0, "totalVotePercent": 0, "url": "/edirne-kesan-ilcesi-yerel-secim-sonuclari/"}, {"chest": {"totalChest": 9, "totalOpenChestPercent": 100, "openChest": 9, "totalVoter": 2689, "totalVote": 2445, "validVote": 2358, "invalidVote": 87, "totalJoinPercent": 90.92599479360356}, "details": [{"candidate": null, "previousTotalVote": null, "previousTotalVotePercent": null, "no": 9, "name": "AK Parti", "totalVote": 1198, "totalVotePercent": 50.80576759966073, "url": "/ak-parti-yerel-secim-sonuclari/"}, {"candidate": null, "previousTotalVote": null, "previousTotalVotePercent": null, "no": 21, "name": "CHP", "totalVote": 1151, "totalVotePercent": 48.812553011026296, "url": "/chp-yerel-secim-sonuclari/"}], "winner": {"candidate": null, "previousTotalVote": null, "previousTotalVotePercent": null, "no": 9, "name": "AK Parti", "totalVote": 1198, "totalVotePercent": 50.80576759966073, "url": "/ak-parti-yerel-secim-sonuclari/"}, "previousWinner": null, "councilPartySummaries": [], "allParties": null, "towns": [], "no": 4857, "name": "KEŞAN-BEĞENDİK", "totalVote": 0, "totalVotePercent": 0, "url": "/edirne-kesan-begendik-ilcesi-yerel-secim-sonuclari/"}, {"chest": {"totalChest": 7, "totalOpenChestPercent": 100, "openChest": 7, "totalVoter": 1682, "totalVote": 1580, "validVote": 1513, "invalidVote": 67, "totalJoinPercent": 93.935790725327}, "details": [{"candidate": null, "previousTotalVote": null, "previousTotalVotePercent": null, "no": 21, "name": "CHP", "totalVote": 850, "totalVotePercent": 56.17977528089887, "url": "/chp-yerel-secim-sonuclari/"}, {"candidate": null, "previousTotalVote": null, "previousTotalVotePercent": null, "no": 9, "name": "AK Parti", "totalVote": 662, "totalVotePercent": 43.75413086582948, "url": "/ak-parti-yerel-secim-sonuclari/"}], "winner": {"candidate": null, "previousTotalVote": null, "previousTotalVotePercent": null, "no": 21, "name": "CHP", "totalVote": 850, "totalVotePercent": 56.17977528089887, "url": "/chp-yerel-secim-sonuclari/"}, "previousWinner": null, "councilPartySummaries": [], "allParties": null, "towns": [], "no": 4854, "name": "KEŞAN-YENİMUHACİR", "totalVote": 0, "totalVotePercent": 0, "url": "/edirne-kesan-yenimuhacir-ilcesi-yerel-secim-sonuclari/"}, {"chest": {"totalChest": 4, "totalOpenChestPercent": 100, "openChest": 4, "totalVoter": 1224, "totalVote": 1121, "validVote": 1060, "invalidVote": 61, "totalJoinPercent": 91.58496732026144}, "details": [{"candidate": {"no": "0", "name": "Zafer Sezgin Geldi", "partyNo": "21", "url": "/chp/edirne/lalapasa/zafer-sezgin-geldi-belediye-baskani-adayi/"}, "previousTotalVote": null, "previousTotalVotePercent": null, "no": 21, "name": "CHP", "totalVote": 516, "totalVotePercent": 48.679245283018865, "url": "/chp-yerel-secim-sonuclari/"}, {"candidate": {"no": "0", "name": "İsmail Arslan", "partyNo": "9", "url": "/ak-parti/edirne/lalapasa/ismail-arslan-belediye-baskani-adayi/"}, "previousTotalVote": null, "previousTotalVotePercent": null, "no": 9, "name": "AK Parti", "totalVote": 389, "totalVotePercent": 36.698113207547166, "url": "/ak-parti-yerel-secim-sonuclari/"}], "winner": {"candidate": {"no": "0", "name": "Zafer Sezgin Geldi", "partyNo": "21", "url": "/chp/edirne/lalapasa/zafer-sezgin-geldi-belediye-baskani-adayi/"}, "previousTotalVote": null, "previousTotalVotePercent": null, "no": 21, "name": "CHP", "totalVote": 516, "totalVotePercent": 48.679245283018865, "url": "/chp-yerel-secim-sonuclari/"}, "previousWinner": null, "councilPartySummaries": [], "allParties": null, "towns": [], "no": 395, "name": "LALAPAŞA", "totalVote": 0, "totalVotePercent": 0, "url": "/edirne-lalapasa-ilcesi-yerel-secim-sonuclari/"}, {"chest": {"totalChest": 8, "totalOpenChestPercent": 100, "openChest": 8, "totalVoter": 2055, "totalVote": 1753, "validVote": 1612, "invalidVote": 141, "totalJoinPercent": 85.30413625304136}, "details": [{"candidate": {"no": "0", "name": "Yunus Atay", "partyNo": "9", "url": "/ak-parti/edirne/meric/yunus-atay-belediye-baskani-adayi/"}, "previousTotalVote": null, "previousTotalVotePercent": null, "no": 9, "name": "AK Parti", "totalVote": 625, "totalVotePercent": 38.77171215880893, "url": "/ak-parti-yerel-secim-sonuclari/"}, {"candidate": {"no": "0", "name": "Erol Dübek", "partyNo": "21", "url": "/chp/edirne/meric/erol-dubek-belediye-baskani-adayi/"}, "previousTotalVote": null, "previousTotalVotePercent": null, "no": 21, "name": "CHP", "totalVote": 567, "totalVotePercent": 35.173697270471465, "url": "/chp-yerel-secim-sonuclari/"}], "winner": {"candidate": {"no": "0", "name": "Yunus Atay", "partyNo": "9", "url": "/ak-parti/edirne/meric/yunus-atay-belediye-baskani-adayi/"}, "previousTotalVote": null, "previousTotalVotePercent": null, "no": 9, "name": "AK Parti", "totalVote": 625, "totalVotePercent": 38.77171215880893, "url": "/ak-parti-yerel-secim-sonuclari/"}, "previousWinner": null, "councilPartySummaries": [], "allParties": null, "towns": [], "no": 416, "name": "MERİÇ", "totalVote": 0, "totalVotePercent": 0, "url": "/edirne-meric-ilcesi-yerel-secim-sonuclari/"}, {"chest": {"totalChest": 7, "totalOpenChestPercent": 100, "openChest": 7, "totalVoter": 1994, "totalVote": 1845, "validVote": 1714, "invalidVote": 131, "totalJoinPercent": 92.52758274824474}, "details": [{"candidate": null, "previousTotalVote": null, "previousTotalVotePercent": null, "no": 21, "name": "CHP", "totalVote": 859, "totalVotePercent": 50.11668611435239, "url": "/chp-yerel-secim-sonuclari/"}, {"candidate": null, "previousTotalVote": null, "previousTotalVotePercent": null, "no": 9, "name": "AK Parti", "totalVote": 624, "totalVotePercent": 36.406067677946325, "url": "/ak-parti-yerel-secim-sonuclari/"}], "winner": {"candidate": null, "previousTotalVote": null, "previousTotalVotePercent": null, "no": 21, "name": "CHP", "totalVote": 859, "totalVotePercent": 50.11668611435239, "url": "/chp-yerel-secim-sonuclari/"}, "previousWinner": null, "councilPartySummaries": [], "allParties": null, "towns": [], "no": 4858, "name": "MERİÇ-KÜPLÜ", "totalVote": 0, "totalVotePercent": 0, "url": "/edirne-meric-kuplu-ilcesi-yerel-secim-sonuclari/"}, {"chest": {"totalChest": 5, "totalOpenChestPercent": 100, "openChest": 5, "totalVoter": 1638, "totalVote": 1528, "validVote": 1431, "invalidVote": 97, "totalJoinPercent": 93.28449328449328}, "details": [{"candidate": null, "previousTotalVote": null, "previousTotalVotePercent": null, "no": 9, "name": "AK Parti", "totalVote": 590, "totalVotePercent": 41.22990915443746, "url": "/ak-parti-yerel-secim-sonuclari/"}, {"candidate": null, "previousTotalVote": null, "previousTotalVotePercent": null, "no": 21, "name": "CHP", "totalVote": 457, "totalVotePercent": 31.93570929419986, "url": "/chp-yerel-secim-sonuclari/"}], "winner": {"candidate": null, "previousTotalVote": null, "previousTotalVotePercent": null, "no": 9, "name": "AK Parti", "totalVote": 590, "totalVotePercent": 41.22990915443746, "url": "/ak-parti-yerel-secim-sonuclari/"}, "previousWinner": null, "councilPartySummaries": [], "allParties": null, "towns": [], "no": 4859, "name": "MERİÇ-SUBAŞI", "totalVote": 0, "totalVotePercent": 0, "url": "/edirne-meric-subasi-ilcesi-yerel-secim-sonuclari/"}, {"chest": {"totalChest": 389, "totalOpenChestPercent": 100, "openChest": 389, "totalVoter": 129084, "totalVote": 102127, "validVote": 98122, "invalidVote": 4005, "totalJoinPercent": 79.11669920361935}, "details": [{"candidate": {"no": "0", "name": "Filiz Gencan Akın", "partyNo": "21", "url": "/chp/edirne/merkez/filiz-gencan-akin-belediye-baskani-adayi/"}, "previousTotalVote": null, "previousTotalVotePercent": null, "no": 21, "name": "CHP", "totalVote": 48088, "totalVotePercent": 49.008377326185766, "url": "/chp-yerel-secim-sonuclari/"}, {"candidate": {"no": "0", "name": "Belgin İba", "partyNo": "9", "url": "/ak-parti/edirne/merkez/belgin-iba-belediye-baskani-adayi/"}, "previousTotalVote": null, "previousTotalVotePercent": null, "no": 9, "name": "AK Parti", "totalVote": 36712, "totalVotePercent": 37.41464707201239, "url": "/ak-parti-yerel-secim-sonuclari/"}], "winner": {"candidate": {"no": "0", "name": "Filiz Gencan Akın", "partyNo": "21", "url": "/chp/edirne/merkez/filiz-gencan-akin-belediye-baskani-adayi/"}, "previousTotalVote": null, "previousTotalVotePercent": null, "no": 21, "name": "CHP", "totalVote": 48088, "totalVotePercent": 49.008377326185766, "url": "/chp-yerel-secim-sonuclari/"}, "previousWinner": null, "councilPartySummaries": [], "allParties": null, "towns": [], "no": 193, "name": "MERKEZ", "totalVote": 0, "totalVotePercent": 0, "url": "/edirne-merkez-ilcesi-yerel-secim-sonuclari/"}, {"chest": {"totalChest": 7, "totalOpenChestPercent": 100, "openChest": 7, "totalVoter": 2206, "totalVote": 1793, "validVote": 1732, "invalidVote": 61, "totalJoinPercent": 81.27833182230282}, "details": [{"candidate": {"no": "0", "name": "Mehmet Ormankıran", "partyNo": "21", "url": "/chp/edirne/suloglu/mehmet-ormankiran-belediye-baskani-adayi/"}, "previousTotalVote": null, "previousTotalVotePercent": null, "no": 21, "name": "CHP", "totalVote": 1005, "totalVotePercent": 58.02540415704388, "url": "/chp-yerel-secim-sonuclari/"}, {"candidate": {"no": "0", "name": "Halil Özgüven", "partyNo": "11", "url": "/mhp/edirne/suloglu/halil-ozguven-belediye-baskani-adayi/"}, "previousTotalVote": null, "previousTotalVotePercent": null, "no": 11, "name": "MHP", "totalVote": 622, "totalVotePercent": 35.91224018475751, "url": "/mhp-yerel-secim-sonuclari/"}], "winner": {"candidate": {"no": "0", "name": "Mehmet Ormankıran", "partyNo": "21", "url": "/chp/edirne/suloglu/mehmet-ormankiran-belediye-baskani-adayi/"}, "previousTotalVote": null, "previousTotalVotePercent": null, "no": 21, "name": "CHP", "totalVote": 1005, "totalVotePercent": 58.02540415704388, "url": "/chp-yerel-secim-sonuclari/"}, "previousWinner": null, "councilPartySummaries": [], "allParties": null, "towns": [], "no": 881, "name": "SÜLOĞLU", "totalVote": 0, "totalVotePercent": 0, "url": "/edirne-suloglu-ilcesi-yerel-secim-sonuclari/"}, {"chest": {"totalChest": 96, "totalOpenChestPercent": 100, "openChest": 96, "totalVoter": 30978, "totalVote": 25121, "validVote": 23881, "invalidVote": 1240, "totalJoinPercent": 81.09303376589838}, "details": [{"candidate": {"no": "0", "name": "Özlem Becan", "partyNo": "21", "url": "/chp/edirne/uzunkopru/ozlem-becan-belediye-baskani-adayi/"}, "previousTotalVote": null, "previousTotalVotePercent": null, "no": 21, "name": "CHP", "totalVote": 8652, "totalVotePercent": 36.22963862484821, "url": "/chp-yerel-secim-sonuclari/"}, {"candidate": {"no": "0", "name": "Mustafa Ravalı", "partyNo": "9", "url": "/ak-parti/edirne/uzunkopru/mustafa-ravali-belediye-baskani-adayi/"}, "previousTotalVote": null, "previousTotalVotePercent": null, "no": 9, "name": "AK Parti", "totalVote": 7280, "totalVotePercent": 30.484485574305932, "url": "/ak-parti-yerel-secim-sonuclari/"}], "winner": {"candidate": {"no": "0", "name": "Özlem Becan", "partyNo": "21", "url": "/chp/edirne/uzunkopru/ozlem-becan-belediye-baskani-adayi/"}, "previousTotalVote": null, "previousTotalVotePercent": null, "no": 21, "name": "CHP", "totalVote": 8652, "totalVotePercent": 36.22963862484821, "url": "/chp-yerel-secim-sonuclari/"}, "previousWinner": null, "councilPartySummaries": [], "allParties": null, "towns": [], "no": 598, "name": "UZUNKÖPRÜ", "totalVote": 0, "totalVotePercent": 0, "url": "/edirne-uzunkopru-ilcesi-yerel-secim-sonuclari/"}, {"chest": {"totalChest": 8, "totalOpenChestPercent": 100, "openChest": 8, "totalVoter": 2254, "totalVote": 2109, "validVote": 1980, "invalidVote": 129, "totalJoinPercent": 93.56699201419698}, "details": [{"candidate": null, "previousTotalVote": null, "previousTotalVotePercent": null, "no": 9, "name": "AK Parti", "totalVote": 976, "totalVotePercent": 49.292929292929294, "url": "/ak-parti-yerel-secim-sonuclari/"}, {"candidate": null, "previousTotalVote": null, "previousTotalVotePercent": null, "no": 21, "name": "CHP", "totalVote": 958, "totalVotePercent": 48.38383838383838, "url": "/chp-yerel-secim-sonuclari/"}], "winner": {"candidate": null, "previousTotalVote": null, "previousTotalVotePercent": null, "no": 9, "name": "AK Parti", "totalVote": 976, "totalVotePercent": 49.292929292929294, "url": "/ak-parti-yerel-secim-sonuclari/"}, "previousWinner": null, "councilPartySummaries": [], "allParties": null, "towns": [], "no": 4862, "name": "UZUNKÖPRÜ-KIRCASALİH", "totalVote": 0, "totalVotePercent": 0, "url": "/edirne-uzunkopru-kircasalih-ilcesi-yerel-secim-sonuclari/"}], "partiesMostVotesCities": null, "numberofWonByParties": [{"wonCount": 6, "no": 21, "name": "CHP", "totalVote": 46260, "totalVotePercent": 23.876498732883604, "url": "/chp-yerel-secim-sonuclari/"}, {"wonCount": 2, "no": 9, "name": "AK Parti", "totalVote": 1645, "totalVotePercent": 0.8490454045740063, "url": "/ak-parti-yerel-secim-sonuclari/"}, {"wonCount": 1, "no": 22, "name": "İYİ Parti", "totalVote": 8026, "totalVotePercent": 4.142515755082659, "url": "/iyi-parti-yerel-secim-sonuclari/"}], "candidateChangeOverview": {"currentWinner": {"candidate": {"no": "0", "name": "Filiz Gencan Akın", "partyNo": "21", "url": "/chp/edirne/merkez/filiz-gencan-akin-belediye-baskani-adayi/"}, "previousTotalVote": null, "previousTotalVotePercent": null, "no": 21, "name": "CHP", "totalVote": 46260, "totalVotePercent": 46.67258565720974, "url": "/chp-yerel-secim-sonuclari/"}, "previousWinner": {"candidate": {"no": "0", "name": "Recep Gürkan", "partyNo": "21", "url": null}, "previousTotalVote": null, "previousTotalVotePercent": null, "no": 21, "name": "CHP", "totalVote": 42388, "totalVotePercent": 44.86879571508717, "url": "/chp-yerel-secim-sonuclari/"}}, "updateDate": "21:26", "mayorVersion": "01 Nisan 2024 21:26", "chest": {"totalChest": 206806, "totalOpenChestPercent": 100, "openChest": 206806, "totalVoter": 61430934, "totalVote": 48256541, "validVote": 46046499, "invalidVote": 2210042, "totalJoinPercent": 78.55413853873685}, "chestCouncil": null, "currentElectionYear": "2024", "previousElectionYear": "2019", "displayName": "31 Mart 2024", "previousDisplayName": "31 Mart 2019", "isBannerActive": false, "showDataDiff": true}