{"cityChest": {"totalChest": 4406, "totalOpenChestPercent": 100, "openChest": 4406, "totalVoter": 1383866, "totalVote": 979238, "validVote": 923514, "invalidVote": 55724, "totalJoinPercent": 70.76104189278442}, "partyMap": [{"chest": {"totalChest": 91, "totalOpenChestPercent": 100, "openChest": 91, "totalVoter": 22511, "totalVote": 19314, "validVote": 18171, "invalidVote": 1143, "totalJoinPercent": 85.79805428457199}, "details": [{"candidate": {"no": "0", "name": "Mehmet Özdemir", "partyNo": "11", "url": "/mhp/gaziantep/araban/mehmet-ozdemir-belediye-baskani-adayi/"}, "previousTotalVote": null, "previousTotalVotePercent": null, "no": 11, "name": "MHP", "totalVote": 5992, "totalVotePercent": 32.97562049419405, "url": "/mhp-yerel-secim-sonuclari/"}, {"candidate": {"no": "0", "name": "Hasan Doğru", "partyNo": "10", "url": "/yeniden-refah/gaziantep/araban/hasan-dogru-belediye-baskani-adayi/"}, "previousTotalVote": null, "previousTotalVotePercent": null, "no": 10, "name": "Yeniden Refah", "totalVote": 4753, "totalVotePercent": 26.15706345275439, "url": "/yeniden-refah-yerel-secim-sonuclari/"}], "winner": {"candidate": {"no": "0", "name": "Mehmet Özdemir", "partyNo": "11", "url": "/mhp/gaziantep/araban/mehmet-ozdemir-belediye-baskani-adayi/"}, "previousTotalVote": null, "previousTotalVotePercent": null, "no": 11, "name": "MHP", "totalVote": 5992, "totalVotePercent": 32.97562049419405, "url": "/mhp-yerel-secim-sonuclari/"}, "previousWinner": null, "councilPartySummaries": [], "allParties": null, "towns": [], "no": 38, "name": "ARABAN", "totalVote": 0, "totalVotePercent": 0, "url": "/gaziantep-araban-ilcesi-yerel-secim-sonuclari/"}, {"chest": {"totalChest": 162, "totalOpenChestPercent": 100, "openChest": 162, "totalVoter": 44372, "totalVote": 36034, "validVote": 34075, "invalidVote": 1959, "totalJoinPercent": 81.20887045884793}, "details": [{"candidate": {"no": "0", "name": "Kemal Vural", "partyNo": "9", "url": "/ak-parti/gaziantep/islahiye/kemal-vural-belediye-baskani-adayi/"}, "previousTotalVote": null, "previousTotalVotePercent": null, "no": 9, "name": "AK Parti", "totalVote": 11568, "totalVotePercent": 33.94864269992663, "url": "/ak-parti-yerel-secim-sonuclari/"}, {"candidate": {"no": "0", "name": "Okan Öztürk", "partyNo": "21", "url": "#"}, "previousTotalVote": null, "previousTotalVotePercent": null, "no": 21, "name": "CHP", "totalVote": 10454, "totalVotePercent": 30.67938371239912, "url": "/chp-yerel-secim-sonuclari/"}], "winner": {"candidate": {"no": "0", "name": "Kemal Vural", "partyNo": "9", "url": "/ak-parti/gaziantep/islahiye/kemal-vural-belediye-baskani-adayi/"}, "previousTotalVote": null, "previousTotalVotePercent": null, "no": 9, "name": "AK Parti", "totalVote": 11568, "totalVotePercent": 33.94864269992663, "url": "/ak-parti-yerel-secim-sonuclari/"}, "previousWinner": null, "councilPartySummaries": [], "allParties": null, "towns": [], "no": 312, "name": "İSLAHİYE", "totalVote": 0, "totalVotePercent": 0, "url": "/gaziantep-islahiye-ilcesi-yerel-secim-sonuclari/"}, {"chest": {"totalChest": 46, "totalOpenChestPercent": 100, "openChest": 46, "totalVoter": 7334, "totalVote": 6678, "validVote": 6381, "invalidVote": 297, "totalJoinPercent": 91.0553586037633}, "details": [{"candidate": {"no": "0", "name": "Mustafa Güzel", "partyNo": "21", "url": "/chp/gaziantep/karkamis/mustafa-guzel-belediye-baskani-adayi/"}, "previousTotalVote": null, "previousTotalVotePercent": null, "no": 21, "name": "CHP", "totalVote": 3194, "totalVotePercent": 50.05485033693778, "url": "/chp-yerel-secim-sonuclari/"}, {"candidate": {"no": "0", "name": "Bülent Tiryaki", "partyNo": "11", "url": "/mhp/gaziantep/karkamis/bulent-tiryaki-belediye-baskani-adayi/"}, "previousTotalVote": null, "previousTotalVotePercent": null, "no": 11, "name": "MHP", "totalVote": 2832, "totalVotePercent": 44.38175834508698, "url": "/mhp-yerel-secim-sonuclari/"}], "winner": {"candidate": {"no": "0", "name": "Mustafa Güzel", "partyNo": "21", "url": "/chp/gaziantep/karkamis/mustafa-guzel-belediye-baskani-adayi/"}, "previousTotalVote": null, "previousTotalVotePercent": null, "no": 21, "name": "CHP", "totalVote": 3194, "totalVotePercent": 50.05485033693778, "url": "/chp-yerel-secim-sonuclari/"}, "previousWinner": null, "councilPartySummaries": [], "allParties": null, "towns": [], "no": 849, "name": "KARKAMIŞ", "totalVote": 0, "totalVotePercent": 0, "url": "/gaziantep-karkamis-ilcesi-yerel-secim-sonuclari/"}, {"chest": {"totalChest": 345, "totalOpenChestPercent": 100, "openChest": 345, "totalVoter": 97181, "totalVote": 79257, "validVote": 74356, "invalidVote": 4901, "totalJoinPercent": 81.5560654860518}, "details": [{"candidate": {"no": "0", "name": "Ali Doğan", "partyNo": "21", "url": "#"}, "previousTotalVote": null, "previousTotalVotePercent": null, "no": 21, "name": "CHP", "totalVote": 28182, "totalVotePercent": 37.90144709236645, "url": "/chp-yerel-secim-sonuclari/"}, {"candidate": {"no": "0", "name": "Haci Fevzi Akdoğan", "partyNo": "9", "url": "/ak-parti/gaziantep/nizip/haci-fevzi-akdogan-belediye-baskani-adayi/"}, "previousTotalVote": null, "previousTotalVotePercent": null, "no": 9, "name": "AK Parti", "totalVote": 23705, "totalVotePercent": 31.880413147560386, "url": "/ak-parti-yerel-secim-sonuclari/"}], "winner": {"candidate": {"no": "0", "name": "Ali Doğan", "partyNo": "21", "url": "#"}, "previousTotalVote": null, "previousTotalVotePercent": null, "no": 21, "name": "CHP", "totalVote": 28182, "totalVotePercent": 37.90144709236645, "url": "/chp-yerel-secim-sonuclari/"}, "previousWinner": null, "councilPartySummaries": [], "allParties": null, "towns": [], "no": 439, "name": "NİZİP", "totalVote": 0, "totalVotePercent": 0, "url": "/gaziantep-nizip-ilcesi-yerel-secim-sonuclari/"}, {"chest": {"totalChest": 105, "totalOpenChestPercent": 100, "openChest": 105, "totalVoter": 27485, "totalVote": 21637, "validVote": 20538, "invalidVote": 1099, "totalJoinPercent": 78.72293978533746}, "details": [{"candidate": {"no": "0", "name": "Mehmet Yıldırır", "partyNo": "9", "url": "/ak-parti/gaziantep/nurdagi/mehmet-yildirir-belediye-baskani-adayi/"}, "previousTotalVote": null, "previousTotalVotePercent": null, "no": 9, "name": "AK Parti", "totalVote": 9687, "totalVotePercent": 47.166228454572014, "url": "/ak-parti-yerel-secim-sonuclari/"}, {"candidate": {"no": "0", "name": "Hasan Dilek", "partyNo": "10", "url": "/yeniden-refah/gaziantep/nurdagi/hasan-dilek-belediye-baskani-adayi/"}, "previousTotalVote": null, "previousTotalVotePercent": null, "no": 10, "name": "Yeniden Refah", "totalVote": 9636, "totalVotePercent": 46.91790826760152, "url": "/yeniden-refah-yerel-secim-sonuclari/"}], "winner": {"candidate": {"no": "0", "name": "Mehmet Yıldırır", "partyNo": "9", "url": "/ak-parti/gaziantep/nurdagi/mehmet-yildirir-belediye-baskani-adayi/"}, "previousTotalVote": null, "previousTotalVotePercent": null, "no": 9, "name": "AK Parti", "totalVote": 9687, "totalVotePercent": 47.166228454572014, "url": "/ak-parti-yerel-secim-sonuclari/"}, "previousWinner": null, "councilPartySummaries": [], "allParties": null, "towns": [], "no": 867, "name": "NURDAĞI", "totalVote": 0, "totalVotePercent": 0, "url": "/gaziantep-nurdagi-ilcesi-yerel-secim-sonuclari/"}, {"chest": {"totalChest": 127, "totalOpenChestPercent": 100, "openChest": 127, "totalVoter": 24784, "totalVote": 21257, "validVote": 20019, "invalidVote": 1238, "totalJoinPercent": 85.76904454486765}, "details": [{"candidate": {"no": "0", "name": "Bekir Öztekin", "partyNo": "10", "url": "#"}, "previousTotalVote": null, "previousTotalVotePercent": null, "no": 10, "name": "Yeniden Refah", "totalVote": 7496, "totalVotePercent": 37.444427793596084, "url": "/yeniden-refah-yerel-secim-sonuclari/"}, {"candidate": {"no": "0", "name": "Mehmet Sait Kılıç", "partyNo": "11", "url": "/mhp/gaziantep/oguzeli/mehmet-sait-kilic-belediye-baskani-adayi/"}, "previousTotalVote": null, "previousTotalVotePercent": null, "no": 11, "name": "MHP", "totalVote": 6456, "totalVotePercent": 32.2493631050502, "url": "/mhp-yerel-secim-sonuclari/"}], "winner": {"candidate": {"no": "0", "name": "Bekir Öztekin", "partyNo": "10", "url": "#"}, "previousTotalVote": null, "previousTotalVotePercent": null, "no": 10, "name": "Yeniden Refah", "totalVote": 7496, "totalVotePercent": 37.444427793596084, "url": "/yeniden-refah-yerel-secim-sonuclari/"}, "previousWinner": null, "councilPartySummaries": [], "allParties": null, "towns": [], "no": 442, "name": "OĞUZELİ", "totalVote": 0, "totalVotePercent": 0, "url": "/gaziantep-oguzeli-ilcesi-yerel-secim-sonuclari/"}, {"chest": {"totalChest": 1840, "totalOpenChestPercent": 100, "openChest": 1840, "totalVoter": 609600, "totalVote": 412224, "validVote": 391285, "invalidVote": 20939, "totalJoinPercent": 67.62204724409449}, "details": [{"candidate": {"no": "0", "name": "Mehmet İhsan Tahmazoğlu", "partyNo": "9", "url": "/ak-parti/gaziantep/sahinbey/mehmet-ihsan-tahmazoglu-belediye-baskani-adayi/"}, "previousTotalVote": null, "previousTotalVotePercent": null, "no": 9, "name": "AK Parti", "totalVote": 216168, "totalVotePercent": 55.24566492454349, "url": "/ak-parti-yerel-secim-sonuclari/"}, {"candidate": {"no": "0", "name": "Arkın Bereketoğlu", "partyNo": "21", "url": "#"}, "previousTotalVote": null, "previousTotalVotePercent": null, "no": 21, "name": "CHP", "totalVote": 83583, "totalVotePercent": 21.36115619050053, "url": "/chp-yerel-secim-sonuclari/"}], "winner": {"candidate": {"no": "0", "name": "Mehmet İhsan Tahmazoğlu", "partyNo": "9", "url": "/ak-parti/gaziantep/sahinbey/mehmet-ihsan-tahmazoglu-belediye-baskani-adayi/"}, "previousTotalVote": null, "previousTotalVotePercent": null, "no": 9, "name": "AK Parti", "totalVote": 216168, "totalVotePercent": 55.24566492454349, "url": "/ak-parti-yerel-secim-sonuclari/"}, "previousWinner": null, "councilPartySummaries": [], "allParties": null, "towns": [], "no": 734, "name": "ŞAHİNBEY", "totalVote": 0, "totalVotePercent": 0, "url": "/gaziantep-sahinbey-ilcesi-yerel-secim-sonuclari/"}, {"chest": {"totalChest": 1627, "totalOpenChestPercent": 100, "openChest": 1627, "totalVoter": 535964, "totalVote": 368003, "validVote": 341757, "invalidVote": 26246, "totalJoinPercent": 68.66188773872872}, "details": [{"candidate": {"no": "0", "name": "Umut Yılmaz", "partyNo": "21", "url": "#"}, "previousTotalVote": null, "previousTotalVotePercent": null, "no": 21, "name": "CHP", "totalVote": 135591, "totalVotePercent": 39.67468113308579, "url": "/chp-yerel-secim-sonuclari/"}, {"candidate": {"no": "0", "name": "Muhammet Rıdvan Fadıloğlu", "partyNo": "9", "url": "/ak-parti/gaziantep/sehitkamil/muhammet-ridvan-fadiloglu-belediye-baskani-adayi/"}, "previousTotalVote": null, "previousTotalVotePercent": null, "no": 9, "name": "AK Parti", "totalVote": 88728, "totalVotePercent": 25.96230655114599, "url": "/ak-parti-yerel-secim-sonuclari/"}], "winner": {"candidate": {"no": "0", "name": "Umut Yılmaz", "partyNo": "21", "url": "#"}, "previousTotalVote": null, "previousTotalVotePercent": null, "no": 21, "name": "CHP", "totalVote": 135591, "totalVotePercent": 39.67468113308579, "url": "/chp-yerel-secim-sonuclari/"}, "previousWinner": null, "councilPartySummaries": [], "allParties": null, "towns": [], "no": 737, "name": "ŞEHİTKAMİL", "totalVote": 0, "totalVotePercent": 0, "url": "/gaziantep-sehitkamil-ilcesi-yerel-secim-sonuclari/"}, {"chest": {"totalChest": 63, "totalOpenChestPercent": 100, "openChest": 63, "totalVoter": 14635, "totalVote": 13114, "validVote": 12493, "invalidVote": 621, "totalJoinPercent": 89.6071062521353}, "details": [{"candidate": {"no": "0", "name": "Mehmet Kaya", "partyNo": "10", "url": "#"}, "previousTotalVote": null, "previousTotalVotePercent": null, "no": 10, "name": "Yeniden Refah", "totalVote": 4483, "totalVotePercent": 35.88409509325222, "url": "/yeniden-refah-yerel-secim-sonuclari/"}, {"candidate": {"no": "0", "name": "Mustafa Kemal Sakaroğlu", "partyNo": "9", "url": "/ak-parti/gaziantep/yavuzeli/mustafa-kemal-sakaroglu-belediye-baskani-adayi/"}, "previousTotalVote": null, "previousTotalVotePercent": null, "no": 9, "name": "AK Parti", "totalVote": 4001, "totalVotePercent": 32.02593452333306, "url": "/ak-parti-yerel-secim-sonuclari/"}], "winner": {"candidate": {"no": "0", "name": "Mehmet Kaya", "partyNo": "10", "url": "#"}, "previousTotalVote": null, "previousTotalVotePercent": null, "no": 10, "name": "Yeniden Refah", "totalVote": 4483, "totalVotePercent": 35.88409509325222, "url": "/yeniden-refah-yerel-secim-sonuclari/"}, "previousWinner": null, "councilPartySummaries": [], "allParties": null, "towns": [], "no": 613, "name": "YAVUZELİ", "totalVote": 0, "totalVotePercent": 0, "url": "/gaziantep-yavuzeli-ilcesi-yerel-secim-sonuclari/"}], "partyTableMap": [{"chest": {"totalChest": 91, "totalOpenChestPercent": 100, "openChest": 91, "totalVoter": 22511, "totalVote": 19314, "validVote": 18171, "invalidVote": 1143, "totalJoinPercent": 85.79805428457199}, "details": [{"candidate": null, "previousTotalVote": 0, "previousTotalVotePercent": 0, "no": 9, "name": "AK Parti", "totalVote": 0, "totalVotePercent": 0, "url": "/ak-parti-yerel-secim-sonuclari/"}, {"candidate": null, "previousTotalVote": 0, "previousTotalVotePercent": 0, "no": 11, "name": "MHP", "totalVote": 5992, "totalVotePercent": 32.97562049419405, "url": "/mhp-yerel-secim-sonuclari/"}, {"candidate": null, "previousTotalVote": 0, "previousTotalVotePercent": 0, "no": 21, "name": "CHP", "totalVote": 3970, "totalVotePercent": 21.847999559738046, "url": "/chp-yerel-secim-sonuclari/"}, {"candidate": null, "previousTotalVote": 0, "previousTotalVotePercent": 0, "no": 10, "name": "Yeniden Refah", "totalVote": 4753, "totalVotePercent": 26.15706345275439, "url": "/yeniden-refah-yerel-secim-sonuclari/"}, {"candidate": null, "previousTotalVote": 0, "previousTotalVotePercent": 0, "no": 87, "name": "DEM Parti", "totalVote": 625, "totalVotePercent": 3.4395465301854604, "url": "/dem-parti-yerel-secim-sonuclari/"}, {"candidate": null, "previousTotalVote": 0, "previousTotalVotePercent": 0, "no": 0, "name": "Diğer", "totalVote": 2831, "totalVotePercent": 15.579769963128062, "url": ""}], "winner": {"candidate": {"no": "0", "name": "Mehmet Özdemir", "partyNo": "11", "url": "/mhp/gaziantep/araban/mehmet-ozdemir-belediye-baskani-adayi/"}, "previousTotalVote": 0, "previousTotalVotePercent": 0, "no": 11, "name": "MHP", "totalVote": 5992, "totalVotePercent": 32.97562049419405, "url": "/mhp-yerel-secim-sonuclari/"}, "previousWinner": {"candidate": {"no": "0", "name": "Hasan Doğru", "partyNo": "21", "url": null}, "previousTotalVote": 0, "previousTotalVotePercent": 0, "no": 21, "name": "CHP", "totalVote": 9049, "totalVotePercent": 51.928153334098475, "url": "/chp-yerel-secim-sonuclari/"}, "councilPartySummaries": [], "allParties": null, "towns": [], "no": 38, "name": "ARABAN", "totalVote": 0, "totalVotePercent": 0, "url": "/gaziantep-araban-ilcesi-yerel-secim-sonuclari/"}, {"chest": {"totalChest": 162, "totalOpenChestPercent": 100, "openChest": 162, "totalVoter": 44372, "totalVote": 36034, "validVote": 34075, "invalidVote": 1959, "totalJoinPercent": 81.20887045884793}, "details": [{"candidate": null, "previousTotalVote": 0, "previousTotalVotePercent": 0, "no": 9, "name": "AK Parti", "totalVote": 11568, "totalVotePercent": 33.94864269992663, "url": "/ak-parti-yerel-secim-sonuclari/"}, {"candidate": null, "previousTotalVote": 0, "previousTotalVotePercent": 0, "no": 11, "name": "MHP", "totalVote": 0, "totalVotePercent": 0, "url": "/mhp-yerel-secim-sonuclari/"}, {"candidate": null, "previousTotalVote": 0, "previousTotalVotePercent": 0, "no": 21, "name": "CHP", "totalVote": 10454, "totalVotePercent": 30.67938371239912, "url": "/chp-yerel-secim-sonuclari/"}, {"candidate": null, "previousTotalVote": 0, "previousTotalVotePercent": 0, "no": 10, "name": "Yeniden Refah", "totalVote": 8861, "totalVotePercent": 26.004402054292004, "url": "/yeniden-refah-yerel-secim-sonuclari/"}, {"candidate": null, "previousTotalVote": 0, "previousTotalVotePercent": 0, "no": 87, "name": "DEM Parti", "totalVote": 361, "totalVotePercent": 1.0594277329420396, "url": "/dem-parti-yerel-secim-sonuclari/"}, {"candidate": null, "previousTotalVote": 0, "previousTotalVotePercent": 0, "no": 0, "name": "Diğer", "totalVote": 2831, "totalVotePercent": 8.308143800440206, "url": ""}], "winner": {"candidate": {"no": "0", "name": "Kemal Vural", "partyNo": "9", "url": "/ak-parti/gaziantep/islahiye/kemal-vural-belediye-baskani-adayi/"}, "previousTotalVote": 0, "previousTotalVotePercent": 0, "no": 9, "name": "AK Parti", "totalVote": 11568, "totalVotePercent": 33.94864269992663, "url": "/ak-parti-yerel-secim-sonuclari/"}, "previousWinner": {"candidate": {"no": "0", "name": "Kemal Vural", "partyNo": "9", "url": null}, "previousTotalVote": 0, "previousTotalVotePercent": 0, "no": 9, "name": "AK Parti", "totalVote": 18183, "totalVotePercent": 49.626091703056765, "url": "/ak-parti-yerel-secim-sonuclari/"}, "councilPartySummaries": [], "allParties": null, "towns": [], "no": 312, "name": "İSLAHİYE", "totalVote": 0, "totalVotePercent": 0, "url": "/gaziantep-islahiye-ilcesi-yerel-secim-sonuclari/"}, {"chest": {"totalChest": 46, "totalOpenChestPercent": 100, "openChest": 46, "totalVoter": 7334, "totalVote": 6678, "validVote": 6381, "invalidVote": 297, "totalJoinPercent": 91.0553586037633}, "details": [{"candidate": null, "previousTotalVote": 0, "previousTotalVotePercent": 0, "no": 9, "name": "AK Parti", "totalVote": 0, "totalVotePercent": 0, "url": "/ak-parti-yerel-secim-sonuclari/"}, {"candidate": null, "previousTotalVote": 0, "previousTotalVotePercent": 0, "no": 11, "name": "MHP", "totalVote": 2832, "totalVotePercent": 44.38175834508698, "url": "/mhp-yerel-secim-sonuclari/"}, {"candidate": null, "previousTotalVote": 0, "previousTotalVotePercent": 0, "no": 21, "name": "CHP", "totalVote": 3194, "totalVotePercent": 50.05485033693778, "url": "/chp-yerel-secim-sonuclari/"}, {"candidate": null, "previousTotalVote": 0, "previousTotalVotePercent": 0, "no": 10, "name": "Yeniden Refah", "totalVote": 70, "totalVotePercent": 1.097006738755681, "url": "/yeniden-refah-yerel-secim-sonuclari/"}, {"candidate": null, "previousTotalVote": 0, "previousTotalVotePercent": 0, "no": 87, "name": "DEM Parti", "totalVote": 18, "totalVotePercent": 0.2820874471086037, "url": "/dem-parti-yerel-secim-sonuclari/"}, {"candidate": null, "previousTotalVote": 0, "previousTotalVotePercent": 0, "no": 0, "name": "Diğer", "totalVote": 267, "totalVotePercent": 4.184297132110954, "url": ""}], "winner": {"candidate": {"no": "0", "name": "Mustafa Güzel", "partyNo": "21", "url": "/chp/gaziantep/karkamis/mustafa-guzel-belediye-baskani-adayi/"}, "previousTotalVote": 0, "previousTotalVotePercent": 0, "no": 21, "name": "CHP", "totalVote": 3194, "totalVotePercent": 50.05485033693778, "url": "/chp-yerel-secim-sonuclari/"}, "previousWinner": {"candidate": {"no": "0", "name": "Ali Doğan", "partyNo": "21", "url": null}, "previousTotalVote": 0, "previousTotalVotePercent": 0, "no": 21, "name": "CHP", "totalVote": 3284, "totalVotePercent": 53.337664446970926, "url": "/chp-yerel-secim-sonuclari/"}, "councilPartySummaries": [], "allParties": null, "towns": [], "no": 849, "name": "KARKAMIŞ", "totalVote": 0, "totalVotePercent": 0, "url": "/gaziantep-karkamis-ilcesi-yerel-secim-sonuclari/"}, {"chest": {"totalChest": 345, "totalOpenChestPercent": 100, "openChest": 345, "totalVoter": 97181, "totalVote": 79257, "validVote": 74356, "invalidVote": 4901, "totalJoinPercent": 81.5560654860518}, "details": [{"candidate": null, "previousTotalVote": 0, "previousTotalVotePercent": 0, "no": 9, "name": "AK Parti", "totalVote": 23705, "totalVotePercent": 31.880413147560386, "url": "/ak-parti-yerel-secim-sonuclari/"}, {"candidate": null, "previousTotalVote": 0, "previousTotalVotePercent": 0, "no": 11, "name": "MHP", "totalVote": 0, "totalVotePercent": 0, "url": "/mhp-yerel-secim-sonuclari/"}, {"candidate": null, "previousTotalVote": 0, "previousTotalVotePercent": 0, "no": 21, "name": "CHP", "totalVote": 28182, "totalVotePercent": 37.90144709236645, "url": "/chp-yerel-secim-sonuclari/"}, {"candidate": null, "previousTotalVote": 0, "previousTotalVotePercent": 0, "no": 10, "name": "Yeniden Refah", "totalVote": 17034, "totalVotePercent": 22.90870945182635, "url": "/yeniden-refah-yerel-secim-sonuclari/"}, {"candidate": null, "previousTotalVote": 0, "previousTotalVotePercent": 0, "no": 87, "name": "DEM Parti", "totalVote": 1926, "totalVotePercent": 2.590241540696111, "url": "/dem-parti-yerel-secim-sonuclari/"}, {"candidate": null, "previousTotalVote": 0, "previousTotalVotePercent": 0, "no": 0, "name": "Diğer", "totalVote": 3509, "totalVotePercent": 4.719188767550702, "url": ""}], "winner": {"candidate": {"no": "0", "name": "Ali Doğan", "partyNo": "21", "url": "#"}, "previousTotalVote": 0, "previousTotalVotePercent": 0, "no": 21, "name": "CHP", "totalVote": 28182, "totalVotePercent": 37.90144709236645, "url": "/chp-yerel-secim-sonuclari/"}, "previousWinner": {"candidate": {"no": "0", "name": "Mehmet Sarı", "partyNo": "9", "url": null}, "previousTotalVote": 0, "previousTotalVotePercent": 0, "no": 9, "name": "AK Parti", "totalVote": 37395, "totalVotePercent": 53.21465163934426, "url": "/ak-parti-yerel-secim-sonuclari/"}, "councilPartySummaries": [], "allParties": null, "towns": [], "no": 439, "name": "NİZİP", "totalVote": 0, "totalVotePercent": 0, "url": "/gaziantep-nizip-ilcesi-yerel-secim-sonuclari/"}, {"chest": {"totalChest": 105, "totalOpenChestPercent": 100, "openChest": 105, "totalVoter": 27485, "totalVote": 21637, "validVote": 20538, "invalidVote": 1099, "totalJoinPercent": 78.72293978533746}, "details": [{"candidate": null, "previousTotalVote": 0, "previousTotalVotePercent": 0, "no": 9, "name": "AK Parti", "totalVote": 9687, "totalVotePercent": 47.166228454572014, "url": "/ak-parti-yerel-secim-sonuclari/"}, {"candidate": null, "previousTotalVote": 0, "previousTotalVotePercent": 0, "no": 11, "name": "MHP", "totalVote": 0, "totalVotePercent": 0, "url": "/mhp-yerel-secim-sonuclari/"}, {"candidate": null, "previousTotalVote": 0, "previousTotalVotePercent": 0, "no": 21, "name": "CHP", "totalVote": 563, "totalVotePercent": 2.7412601032232935, "url": "/chp-yerel-secim-sonuclari/"}, {"candidate": null, "previousTotalVote": 0, "previousTotalVotePercent": 0, "no": 10, "name": "Yeniden Refah", "totalVote": 9636, "totalVotePercent": 46.91790826760152, "url": "/yeniden-refah-yerel-secim-sonuclari/"}, {"candidate": null, "previousTotalVote": 0, "previousTotalVotePercent": 0, "no": 87, "name": "DEM Parti", "totalVote": 111, "totalVotePercent": 0.5404615834063686, "url": "/dem-parti-yerel-secim-sonuclari/"}, {"candidate": null, "previousTotalVote": 0, "previousTotalVotePercent": 0, "no": 0, "name": "Diğer", "totalVote": 541, "totalVotePercent": 2.634141591196806, "url": ""}], "winner": {"candidate": {"no": "0", "name": "Mehmet Yıldırır", "partyNo": "9", "url": "/ak-parti/gaziantep/nurdagi/mehmet-yildirir-belediye-baskani-adayi/"}, "previousTotalVote": 0, "previousTotalVotePercent": 0, "no": 9, "name": "AK Parti", "totalVote": 9687, "totalVotePercent": 47.166228454572014, "url": "/ak-parti-yerel-secim-sonuclari/"}, "previousWinner": {"candidate": {"no": "0", "name": "Ökkeş Kavak", "partyNo": "9", "url": null}, "previousTotalVote": 0, "previousTotalVotePercent": 0, "no": 9, "name": "AK Parti", "totalVote": 8873, "totalVotePercent": 39.60453490448134, "url": "/ak-parti-yerel-secim-sonuclari/"}, "councilPartySummaries": [], "allParties": null, "towns": [], "no": 867, "name": "NURDAĞI", "totalVote": 0, "totalVotePercent": 0, "url": "/gaziantep-nurdagi-ilcesi-yerel-secim-sonuclari/"}, {"chest": {"totalChest": 127, "totalOpenChestPercent": 100, "openChest": 127, "totalVoter": 24784, "totalVote": 21257, "validVote": 20019, "invalidVote": 1238, "totalJoinPercent": 85.76904454486765}, "details": [{"candidate": null, "previousTotalVote": 0, "previousTotalVotePercent": 0, "no": 9, "name": "AK Parti", "totalVote": 0, "totalVotePercent": 0, "url": "/ak-parti-yerel-secim-sonuclari/"}, {"candidate": null, "previousTotalVote": 0, "previousTotalVotePercent": 0, "no": 11, "name": "MHP", "totalVote": 6456, "totalVotePercent": 32.2493631050502, "url": "/mhp-yerel-secim-sonuclari/"}, {"candidate": null, "previousTotalVote": 0, "previousTotalVotePercent": 0, "no": 21, "name": "CHP", "totalVote": 4062, "totalVotePercent": 20.29072381237824, "url": "/chp-yerel-secim-sonuclari/"}, {"candidate": null, "previousTotalVote": 0, "previousTotalVotePercent": 0, "no": 10, "name": "Yeniden Refah", "totalVote": 7496, "totalVotePercent": 37.444427793596084, "url": "/yeniden-refah-yerel-secim-sonuclari/"}, {"candidate": null, "previousTotalVote": 0, "previousTotalVotePercent": 0, "no": 87, "name": "DEM Parti", "totalVote": 93, "totalVotePercent": 0.46455866926419903, "url": "/dem-parti-yerel-secim-sonuclari/"}, {"candidate": null, "previousTotalVote": 0, "previousTotalVotePercent": 0, "no": 0, "name": "Diğer", "totalVote": 1912, "totalVotePercent": 9.550926619711275, "url": ""}], "winner": {"candidate": {"no": "0", "name": "Bekir Öztekin", "partyNo": "10", "url": "#"}, "previousTotalVote": 0, "previousTotalVotePercent": 0, "no": 10, "name": "Yeniden Refah", "totalVote": 7496, "totalVotePercent": 37.444427793596084, "url": "/yeniden-refah-yerel-secim-sonuclari/"}, "previousWinner": {"candidate": {"no": "0", "name": "Mehmet Sait Kılıç", "partyNo": "11", "url": null}, "previousTotalVote": 0, "previousTotalVotePercent": 0, "no": 11, "name": "MHP", "totalVote": 10174, "totalVotePercent": 57.321539241647415, "url": "/mhp-yerel-secim-sonuclari/"}, "councilPartySummaries": [], "allParties": null, "towns": [], "no": 442, "name": "OĞUZELİ", "totalVote": 0, "totalVotePercent": 0, "url": "/gaziantep-oguzeli-ilcesi-yerel-secim-sonuclari/"}, {"chest": {"totalChest": 1840, "totalOpenChestPercent": 100, "openChest": 1840, "totalVoter": 609600, "totalVote": 412224, "validVote": 391285, "invalidVote": 20939, "totalJoinPercent": 67.62204724409449}, "details": [{"candidate": null, "previousTotalVote": 0, "previousTotalVotePercent": 0, "no": 9, "name": "AK Parti", "totalVote": 216168, "totalVotePercent": 55.24566492454349, "url": "/ak-parti-yerel-secim-sonuclari/"}, {"candidate": null, "previousTotalVote": 0, "previousTotalVotePercent": 0, "no": 11, "name": "MHP", "totalVote": 0, "totalVotePercent": 0, "url": "/mhp-yerel-secim-sonuclari/"}, {"candidate": null, "previousTotalVote": 0, "previousTotalVotePercent": 0, "no": 21, "name": "CHP", "totalVote": 83583, "totalVotePercent": 21.36115619050053, "url": "/chp-yerel-secim-sonuclari/"}, {"candidate": null, "previousTotalVote": 0, "previousTotalVotePercent": 0, "no": 10, "name": "Yeniden Refah", "totalVote": 36684, "totalVotePercent": 9.375263554697982, "url": "/yeniden-refah-yerel-secim-sonuclari/"}, {"candidate": null, "previousTotalVote": 0, "previousTotalVotePercent": 0, "no": 87, "name": "DEM Parti", "totalVote": 20817, "totalVotePercent": 5.320163052506485, "url": "/dem-parti-yerel-secim-sonuclari/"}, {"candidate": null, "previousTotalVote": 0, "previousTotalVotePercent": 0, "no": 0, "name": "Diğer", "totalVote": 34033, "totalVotePercent": 8.69775227775151, "url": ""}], "winner": {"candidate": {"no": "0", "name": "Mehmet İhsan Tahmazoğlu", "partyNo": "9", "url": "/ak-parti/gaziantep/sahinbey/mehmet-ihsan-tahmazoglu-belediye-baskani-adayi/"}, "previousTotalVote": 0, "previousTotalVotePercent": 0, "no": 9, "name": "AK Parti", "totalVote": 216168, "totalVotePercent": 55.24566492454349, "url": "/ak-parti-yerel-secim-sonuclari/"}, "previousWinner": {"candidate": {"no": "0", "name": "Mehmet İhsan Tahmazoğlu", "partyNo": "9", "url": null}, "previousTotalVote": 0, "previousTotalVotePercent": 0, "no": 9, "name": "AK Parti", "totalVote": 240033, "totalVotePercent": 60.25045683648266, "url": "/ak-parti-yerel-secim-sonuclari/"}, "councilPartySummaries": [], "allParties": null, "towns": [], "no": 734, "name": "ŞAHİNBEY", "totalVote": 0, "totalVotePercent": 0, "url": "/gaziantep-sahinbey-ilcesi-yerel-secim-sonuclari/"}, {"chest": {"totalChest": 1627, "totalOpenChestPercent": 100, "openChest": 1627, "totalVoter": 535964, "totalVote": 368003, "validVote": 341757, "invalidVote": 26246, "totalJoinPercent": 68.66188773872872}, "details": [{"candidate": null, "previousTotalVote": 0, "previousTotalVotePercent": 0, "no": 9, "name": "AK Parti", "totalVote": 88728, "totalVotePercent": 25.96230655114599, "url": "/ak-parti-yerel-secim-sonuclari/"}, {"candidate": null, "previousTotalVote": 0, "previousTotalVotePercent": 0, "no": 11, "name": "MHP", "totalVote": 0, "totalVotePercent": 0, "url": "/mhp-yerel-secim-sonuclari/"}, {"candidate": null, "previousTotalVote": 0, "previousTotalVotePercent": 0, "no": 21, "name": "CHP", "totalVote": 135591, "totalVotePercent": 39.67468113308579, "url": "/chp-yerel-secim-sonuclari/"}, {"candidate": null, "previousTotalVote": 0, "previousTotalVotePercent": 0, "no": 10, "name": "Yeniden Refah", "totalVote": 52493, "totalVotePercent": 15.35974391160971, "url": "/yeniden-refah-yerel-secim-sonuclari/"}, {"candidate": null, "previousTotalVote": 0, "previousTotalVotePercent": 0, "no": 87, "name": "DEM Parti", "totalVote": 20508, "totalVotePercent": 6.000754922357113, "url": "/dem-parti-yerel-secim-sonuclari/"}, {"candidate": null, "previousTotalVote": 0, "previousTotalVotePercent": 0, "no": 0, "name": "Diğer", "totalVote": 44437, "totalVotePercent": 13.002513481801397, "url": ""}], "winner": {"candidate": {"no": "0", "name": "Umut Yılmaz", "partyNo": "21", "url": "#"}, "previousTotalVote": 0, "previousTotalVotePercent": 0, "no": 21, "name": "CHP", "totalVote": 135591, "totalVotePercent": 39.67468113308579, "url": "/chp-yerel-secim-sonuclari/"}, "previousWinner": {"candidate": {"no": "0", "name": "Muhammet Rıdvan Fadıloğlu", "partyNo": "9", "url": null}, "previousTotalVote": 0, "previousTotalVotePercent": 0, "no": 9, "name": "AK Parti", "totalVote": 178824, "totalVotePercent": 53.482793891577295, "url": "/ak-parti-yerel-secim-sonuclari/"}, "councilPartySummaries": [], "allParties": null, "towns": [], "no": 737, "name": "ŞEHİTKAMİL", "totalVote": 0, "totalVotePercent": 0, "url": "/gaziantep-sehitkamil-ilcesi-yerel-secim-sonuclari/"}, {"chest": {"totalChest": 63, "totalOpenChestPercent": 100, "openChest": 63, "totalVoter": 14635, "totalVote": 13114, "validVote": 12493, "invalidVote": 621, "totalJoinPercent": 89.6071062521353}, "details": [{"candidate": null, "previousTotalVote": 0, "previousTotalVotePercent": 0, "no": 9, "name": "AK Parti", "totalVote": 4001, "totalVotePercent": 32.02593452333306, "url": "/ak-parti-yerel-secim-sonuclari/"}, {"candidate": null, "previousTotalVote": 0, "previousTotalVotePercent": 0, "no": 11, "name": "MHP", "totalVote": 0, "totalVotePercent": 0, "url": "/mhp-yerel-secim-sonuclari/"}, {"candidate": null, "previousTotalVote": 0, "previousTotalVotePercent": 0, "no": 21, "name": "CHP", "totalVote": 3647, "totalVotePercent": 29.192347714720242, "url": "/chp-yerel-secim-sonuclari/"}, {"candidate": null, "previousTotalVote": 0, "previousTotalVotePercent": 0, "no": 10, "name": "Yeniden Refah", "totalVote": 4483, "totalVotePercent": 35.88409509325222, "url": "/yeniden-refah-yerel-secim-sonuclari/"}, {"candidate": null, "previousTotalVote": 0, "previousTotalVotePercent": 0, "no": 87, "name": "DEM Parti", "totalVote": 0, "totalVotePercent": 0, "url": "/dem-parti-yerel-secim-sonuclari/"}, {"candidate": null, "previousTotalVote": 0, "previousTotalVotePercent": 0, "no": 0, "name": "Diğer", "totalVote": 362, "totalVotePercent": 2.897622668694469, "url": ""}], "winner": {"candidate": {"no": "0", "name": "Mehmet Kaya", "partyNo": "10", "url": "#"}, "previousTotalVote": 0, "previousTotalVotePercent": 0, "no": 10, "name": "Yeniden Refah", "totalVote": 4483, "totalVotePercent": 35.88409509325222, "url": "/yeniden-refah-yerel-secim-sonuclari/"}, "previousWinner": {"candidate": {"no": "0", "name": "Mustafa Kemal Sakaroğlu", "partyNo": "9", "url": null}, "previousTotalVote": 0, "previousTotalVotePercent": 0, "no": 9, "name": "AK Parti", "totalVote": 6371, "totalVotePercent": 53.492863140218304, "url": "/ak-parti-yerel-secim-sonuclari/"}, "councilPartySummaries": [], "allParties": null, "towns": [], "no": 613, "name": "YAVUZELİ", "totalVote": 0, "totalVotePercent": 0, "url": "/gaziantep-yavuzeli-ilcesi-yerel-secim-sonuclari/"}], "partySummaries": [{"candidate": {"no": "0", "name": "Fatma Şahin", "partyNo": "9", "url": "/ak-parti/gaziantep/fatma-sahin-belediye-baskani-adayi/"}, "previousTotalVote": null, "previousTotalVotePercent": null, "no": 9, "name": "AK Parti", "totalVote": 358590, "totalVotePercent": 38.82886453264379, "url": "/ak-parti-yerel-secim-sonuclari/"}, {"candidate": {"no": "0", "name": "Muzaffer Ertürk", "partyNo": "21", "url": "#"}, "previousTotalVote": null, "previousTotalVotePercent": null, "no": 21, "name": "CHP", "totalVote": 259679, "totalVotePercent": 28.118577520210845, "url": "/chp-yerel-secim-sonuclari/"}, {"candidate": {"no": "0", "name": "Şükrü Yılmaz", "partyNo": "10", "url": "#"}, "previousTotalVote": null, "previousTotalVotePercent": null, "no": 10, "name": "Yeniden Refah", "totalVote": 159158, "totalVotePercent": 17.2339563883168, "url": "/yeniden-refah-yerel-secim-sonuclari/"}, {"candidate": {"no": "0", "name": "Selman Tutumlu", "partyNo": "87", "url": "#"}, "previousTotalVote": null, "previousTotalVotePercent": null, "no": 87, "name": "DEM Parti", "totalVote": 50517, "totalVotePercent": 5.470084914792846, "url": "/dem-parti-yerel-secim-sonuclari/"}, {"candidate": {"no": "0", "name": "Mehmet Pamuk", "partyNo": "24", "url": "#"}, "previousTotalVote": null, "previousTotalVotePercent": null, "no": 24, "name": "Zafer Partisi", "totalVote": 23636, "totalVotePercent": 2.5593548121631073, "url": "/zafer-partisi-yerel-secim-sonuclari/"}, {"candidate": {"no": "0", "name": "Yaşar Sağlam", "partyNo": "22", "url": "#"}, "previousTotalVote": null, "previousTotalVotePercent": null, "no": 22, "name": "İYİ Parti", "totalVote": 15898, "totalVotePercent": 1.7214682181320478, "url": "/iyi-parti-yerel-secim-sonuclari/"}, {"candidate": {"no": "0", "name": "Mehmet Nakşi Erat", "partyNo": "33", "url": "#"}, "previousTotalVote": null, "previousTotalVotePercent": null, "no": 33, "name": "HÜDA PAR", "totalVote": 13929, "totalVotePercent": 1.5082608384929737, "url": "/huda-par-yerel-secim-sonuclari/"}, {"candidate": {"no": "0", "name": "Ahmet Cengiz", "partyNo": "34", "url": "#"}, "previousTotalVote": null, "previousTotalVotePercent": null, "no": 34, "name": "Saadet", "totalVote": 12810, "totalVotePercent": 1.387093211364419, "url": "/saadet-yerel-secim-sonuclari/"}, {"candidate": {"no": "0", "name": "Ekrem Kurt", "partyNo": "27", "url": "#"}, "previousTotalVote": null, "previousTotalVotePercent": null, "no": 27, "name": "DEVA Partisi", "totalVote": 4786, "totalVotePercent": 0.5182379476651139, "url": "/deva-partisi-yerel-secim-sonuclari/"}, {"candidate": {"no": "2024679", "name": "Ramazan Karabudak", "partyNo": "0", "url": "#"}, "previousTotalVote": null, "previousTotalVotePercent": null, "no": 0, "name": "Bağımsız", "totalVote": 3029, "totalVotePercent": 0.327986365122781, "url": ""}, {"candidate": {"no": "0", "name": "Ömer Faruk Boztepe", "partyNo": "25", "url": "#"}, "previousTotalVote": null, "previousTotalVotePercent": null, "no": 25, "name": "BTP", "totalVote": 2910, "totalVotePercent": 0.3151007997713083, "url": "/btp-yerel-secim-sonuclari/"}, {"candidate": {"no": "0", "name": "Abdülkadir Öz", "partyNo": "28", "url": "#"}, "previousTotalVote": null, "previousTotalVotePercent": null, "no": 28, "name": "DP", "totalVote": 1639, "totalVotePercent": 0.17747429925263722, "url": "/dp-yerel-secim-sonuclari/"}, {"candidate": {"no": "0", "name": "Mehmet Bozkurt", "partyNo": "29", "url": "#"}, "previousTotalVote": null, "previousTotalVotePercent": null, "no": 29, "name": "DSP", "totalVote": 1606, "totalVotePercent": 0.1739009912139935, "url": "/dsp-yerel-secim-sonuclari/"}, {"candidate": {"no": "0", "name": "Salih Sezgin", "partyNo": "35", "url": "#"}, "previousTotalVote": null, "previousTotalVotePercent": null, "no": 35, "name": "YTP", "totalVote": 1587, "totalVotePercent": 0.17184363204022896, "url": "/ytp-yerel-secim-sonuclari/"}, {"candidate": {"no": "0", "name": "Ömer Atalay", "partyNo": "13", "url": "#"}, "previousTotalVote": null, "previousTotalVotePercent": null, "no": 13, "name": "TİP", "totalVote": 1581, "totalVotePercent": 0.17119393966956645, "url": "/tip-yerel-secim-sonuclari/"}, {"candidate": {"no": "0", "name": "Fatma Yücetaş", "partyNo": "3", "url": "#"}, "previousTotalVote": null, "previousTotalVotePercent": null, "no": 3, "name": "TKP", "totalVote": 1354, "totalVotePercent": 0.14661391164616888, "url": "/tkp-yerel-secim-sonuclari/"}, {"candidate": {"no": "0", "name": "Önder Beşe", "partyNo": "15", "url": "#"}, "previousTotalVote": null, "previousTotalVotePercent": null, "no": 15, "name": "ANAP", "totalVote": 1317, "totalVotePercent": 0.14260747536041685, "url": "/anap-yerel-secim-sonuclari/"}, {"candidate": {"no": "0", "name": "Hüseyin Özcan", "partyNo": "31", "url": "#"}, "previousTotalVote": null, "previousTotalVotePercent": null, "no": 31, "name": "Gelecek Partisi", "totalVote": 1303, "totalVotePercent": 0.1410915264955377, "url": "/gelecek-partisi-yerel-secim-sonuclari/"}, {"candidate": {"no": "0", "name": "Ali Galip Emrullah", "partyNo": "1", "url": "#"}, "previousTotalVote": null, "previousTotalVotePercent": null, "no": 1, "name": "Millet", "totalVote": 1130, "totalVotePercent": 0.12235872980810253, "url": "/millet-yerel-secim-sonuclari/"}, {"candidate": {"no": "0", "name": "Mustafa Gökçayır", "partyNo": "19", "url": "#"}, "previousTotalVote": null, "previousTotalVotePercent": null, "no": 19, "name": "Vatan", "totalVote": 986, "totalVotePercent": 0.10676611291220274, "url": "/vatan-yerel-secim-sonuclari/"}, {"candidate": {"no": "0", "name": "Osman Dost", "partyNo": "18", "url": "#"}, "previousTotalVote": null, "previousTotalVotePercent": null, "no": 18, "name": "Milli Yol", "totalVote": 893, "totalVotePercent": 0.09669588116693412, "url": "/milli-yol-yerel-secim-sonuclari/"}, {"candidate": {"no": "0", "name": "Ayfer Akay", "partyNo": "14", "url": "#"}, "previousTotalVote": null, "previousTotalVotePercent": null, "no": 14, "name": "ABP", "totalVote": 880, "totalVotePercent": 0.09528821436383206, "url": "/abp-yerel-secim-sonuclari/"}, {"candidate": {"no": "2024677", "name": "Mahmut Karalar", "partyNo": "0", "url": "#"}, "previousTotalVote": null, "previousTotalVotePercent": null, "no": 0, "name": "Bağımsız", "totalVote": 853, "totalVotePercent": 0.09236459869585084, "url": ""}, {"candidate": {"no": "0", "name": "Hüseyin İnce", "partyNo": "88", "url": "#"}, "previousTotalVote": null, "previousTotalVotePercent": null, "no": 88, "name": "AB Parti", "totalVote": 765, "totalVotePercent": 0.08283577725946764, "url": "/ab-parti-yerel-secim-sonuclari/"}, {"candidate": {"no": "0", "name": "Ayşe Çalışkan", "partyNo": "2", "url": "#"}, "previousTotalVote": null, "previousTotalVotePercent": null, "no": 2, "name": "HAK-PAR", "totalVote": 735, "totalVotePercent": 0.07958731540615518, "url": "/hak-par-yerel-secim-sonuclari/"}, {"candidate": {"no": "0", "name": "Murat Deniz", "partyNo": "23", "url": "#"}, "previousTotalVote": null, "previousTotalVotePercent": null, "no": 23, "name": "AP", "totalVote": 583, "totalVotePercent": 0.06312844201603873, "url": "/ap-yerel-secim-sonuclari/"}, {"candidate": {"no": "0", "name": "Deniz Korkmaz", "partyNo": "17", "url": "#"}, "previousTotalVote": null, "previousTotalVotePercent": null, "no": 17, "name": "HKP", "totalVote": 530, "totalVotePercent": 0.0573894927418534, "url": "/hkp-yerel-secim-sonuclari/"}, {"candidate": {"no": "0", "name": "Abdullah Tutuş", "partyNo": "4", "url": "#"}, "previousTotalVote": null, "previousTotalVotePercent": null, "no": 4, "name": "TKH", "totalVote": 419, "totalVotePercent": 0.04537018388459731, "url": "/tkh-yerel-secim-sonuclari/"}, {"candidate": {"no": "2024678", "name": "Hasan Şahin Karacaoğlu", "partyNo": "0", "url": "#"}, "previousTotalVote": null, "previousTotalVotePercent": null, "no": 0, "name": "Bağımsız", "totalVote": 411, "totalVotePercent": 0.04450392739038066, "url": ""}], "councilPartySummaries": [{"previousTotalVote": 481466, "previousTotalVotePercent": 52.658541840521394, "candidate": null, "previousCandidate": null, "no": 9, "name": "AK Parti", "totalVote": 323749, "totalVotePercent": 35.464146321959575, "url": "/ak-parti-yerel-secim-sonuclari/"}, {"previousTotalVote": 174670, "previousTotalVotePercent": 19.103877539190457, "candidate": null, "previousCandidate": null, "no": 21, "name": "CHP", "totalVote": 259195, "totalVotePercent": 28.392765401345834, "url": "/chp-yerel-secim-sonuclari/"}, {"previousTotalVote": null, "previousTotalVotePercent": null, "candidate": null, "previousCandidate": null, "no": 10, "name": "Yeniden Refah", "totalVote": 151752, "totalVotePercent": 16.62323322280535, "url": "/yeniden-refah-yerel-secim-sonuclari/"}, {"previousTotalVote": null, "previousTotalVotePercent": null, "candidate": null, "previousCandidate": null, "no": 87, "name": "DEM Parti", "totalVote": 50590, "totalVotePercent": 5.5417349935534475, "url": "/dem-parti-yerel-secim-sonuclari/"}, {"previousTotalVote": null, "previousTotalVotePercent": null, "candidate": null, "previousCandidate": null, "no": 24, "name": "Zafer Partisi", "totalVote": 23424, "totalVotePercent": 2.5659142219607816, "url": "/zafer-partisi-yerel-secim-sonuclari/"}, {"previousTotalVote": 112811, "previousTotalVotePercent": 12.338280924449617, "candidate": null, "previousCandidate": null, "no": 22, "name": "İYİ Parti", "totalVote": 20535, "totalVotePercent": 2.24944708623483, "url": "/iyi-parti-yerel-secim-sonuclari/"}, {"previousTotalVote": null, "previousTotalVotePercent": null, "candidate": null, "previousCandidate": null, "no": 33, "name": "HÜDA PAR", "totalVote": 16480, "totalVotePercent": 1.8052538583467248, "url": "/huda-par-yerel-secim-sonuclari/"}, {"previousTotalVote": 13317, "previousTotalVotePercent": 1.4564970354920668, "candidate": null, "previousCandidate": null, "no": 11, "name": "MHP", "totalVote": 14750, "totalVotePercent": 1.6157460200615408, "url": "/mhp-yerel-secim-sonuclari/"}, {"previousTotalVote": 14351, "previousTotalVotePercent": 1.5695869156977285, "candidate": null, "previousCandidate": null, "no": 8, "name": "Büyük Birlik", "totalVote": 11495, "totalVotePercent": 1.2591864746174517, "url": "/buyuk-birlik-yerel-secim-sonuclari/"}, {"previousTotalVote": 17684, "previousTotalVotePercent": 1.9341213167861913, "candidate": null, "previousCandidate": null, "no": 34, "name": "Saadet", "totalVote": 11257, "totalVotePercent": 1.2331154540903568, "url": "/saadet-yerel-secim-sonuclari/"}, {"previousTotalVote": null, "previousTotalVotePercent": null, "candidate": null, "previousCandidate": null, "no": 27, "name": "DEVA Partisi", "totalVote": 5951, "totalVotePercent": 0.6518850552804223, "url": "/deva-partisi-yerel-secim-sonuclari/"}, {"previousTotalVote": 2897, "previousTotalVotePercent": 0.3168485328392669, "candidate": null, "previousCandidate": null, "no": 25, "name": "BTP", "totalVote": 4221, "totalVotePercent": 0.4623772169952382, "url": "/btp-yerel-secim-sonuclari/"}, {"previousTotalVote": null, "previousTotalVotePercent": null, "candidate": null, "previousCandidate": null, "no": 7, "name": "Memleket", "totalVote": 2512, "totalVotePercent": 0.2751697628742095, "url": "/memleket-yerel-secim-sonuclari/"}, {"previousTotalVote": 56325, "previousTotalVotePercent": 6.1603360759999, "candidate": null, "previousCandidate": null, "no": 29, "name": "DSP", "totalVote": 2226, "totalVotePercent": 0.2438407214004739, "url": "/dsp-yerel-secim-sonuclari/"}, {"previousTotalVote": null, "previousTotalVotePercent": null, "candidate": null, "previousCandidate": null, "no": 13, "name": "TİP", "totalVote": 1959, "totalVotePercent": 0.21459297988478362, "url": "/tip-yerel-secim-sonuclari/"}, {"previousTotalVote": 6599, "previousTotalVotePercent": 0.7217409279276225, "candidate": null, "previousCandidate": null, "no": 28, "name": "DP", "totalVote": 1944, "totalVotePercent": 0.21294984833895833, "url": "/dp-yerel-secim-sonuclari/"}, {"previousTotalVote": 2133, "previousTotalVotePercent": 0.23328889214572188, "candidate": null, "previousCandidate": null, "no": 3, "name": "TKP", "totalVote": 1412, "totalVotePercent": 0.15467344951368783, "url": "/tkp-yerel-secim-sonuclari/"}, {"previousTotalVote": null, "previousTotalVotePercent": null, "candidate": null, "previousCandidate": null, "no": 31, "name": "Gelecek Partisi", "totalVote": 1412, "totalVotePercent": 0.15467344951368783, "url": "/gelecek-partisi-yerel-secim-sonuclari/"}, {"previousTotalVote": null, "previousTotalVotePercent": null, "candidate": null, "previousCandidate": null, "no": 15, "name": "ANAP", "totalVote": 1289, "totalVotePercent": 0.1411997708379204, "url": "/anap-yerel-secim-sonuclari/"}, {"previousTotalVote": null, "previousTotalVotePercent": null, "candidate": null, "previousCandidate": null, "no": 1, "name": "Millet", "totalVote": 1211, "totalVotePercent": 0.13265548679962888, "url": "/millet-yerel-secim-sonuclari/"}, {"previousTotalVote": null, "previousTotalVotePercent": null, "candidate": null, "previousCandidate": null, "no": 5, "name": "Sol Parti", "totalVote": 985, "totalVotePercent": 0.10789897150919442, "url": "/sol-parti-yerel-secim-sonuclari/"}, {"previousTotalVote": 1621, "previousTotalVotePercent": 0.17729080833015246, "candidate": null, "previousCandidate": null, "no": 19, "name": "Vatan", "totalVote": 976, "totalVotePercent": 0.10691309258169925, "url": "/vatan-yerel-secim-sonuclari/"}, {"previousTotalVote": null, "previousTotalVotePercent": null, "candidate": null, "previousCandidate": null, "no": 4, "name": "TKH", "totalVote": 600, "totalVotePercent": 0.06572526183301183, "url": "/tkh-yerel-secim-sonuclari/"}, {"previousTotalVote": null, "previousTotalVotePercent": null, "candidate": null, "previousCandidate": null, "no": 18, "name": "Milli Yol", "totalVote": 578, "totalVotePercent": 0.06331533556580139, "url": "/milli-yol-yerel-secim-sonuclari/"}, {"previousTotalVote": null, "previousTotalVotePercent": null, "candidate": null, "previousCandidate": null, "no": 14, "name": "ABP", "totalVote": 554, "totalVotePercent": 0.06068632509248092, "url": "/abp-yerel-secim-sonuclari/"}, {"previousTotalVote": 117, "previousTotalVotePercent": 0.012796437121917234, "candidate": null, "previousCandidate": null, "no": 0, "name": "SERVET PASLIYER", "totalVote": 470, "totalVotePercent": 0.05148478843585926, "url": ""}, {"previousTotalVote": 117, "previousTotalVotePercent": 0.012796437121917234, "candidate": null, "previousCandidate": null, "no": 0, "name": "MEHMET NACİ ÖZKALALI", "totalVote": 333, "totalVotePercent": 0.036477520317321564, "url": ""}, {"previousTotalVote": 117, "previousTotalVotePercent": 0.012796437121917234, "candidate": null, "previousCandidate": null, "no": 0, "name": "CEMAL KARAKUZULU", "totalVote": 293, "totalVotePercent": 0.032095836195120776, "url": ""}, {"previousTotalVote": 117, "previousTotalVotePercent": 0.012796437121917234, "candidate": null, "previousCandidate": null, "no": 0, "name": "MEHMET ÇÖPOĞLU", "totalVote": 133, "totalVotePercent": 0.014569099706317621, "url": ""}, {"previousTotalVote": 117, "previousTotalVotePercent": 0.012796437121917234, "candidate": null, "previousCandidate": null, "no": 0, "name": "EMİNE ŞAHİN", "totalVote": 133, "totalVotePercent": 0.014569099706317621, "url": ""}, {"previousTotalVote": 117, "previousTotalVotePercent": 0.012796437121917234, "candidate": null, "previousCandidate": null, "no": 0, "name": "MUSTAFA KARA", "totalVote": 125, "totalVotePercent": 0.013692762881877464, "url": ""}, {"previousTotalVote": 117, "previousTotalVotePercent": 0.012796437121917234, "candidate": null, "previousCandidate": null, "no": 0, "name": "TUĞBA AKKUŞ", "totalVote": 103, "totalVotePercent": 0.01128283661466703, "url": ""}, {"previousTotalVote": 117, "previousTotalVotePercent": 0.012796437121917234, "candidate": null, "previousCandidate": null, "no": 0, "name": "BİLAL ÇELİK", "totalVote": 73, "totalVotePercent": 0.007996573523016439, "url": ""}, {"previousTotalVote": null, "previousTotalVotePercent": null, "candidate": null, "previousCandidate": null, "no": 23, "name": "AP", "totalVote": 70, "totalVotePercent": 0.00766794721385138, "url": "/ap-yerel-secim-sonuclari/"}, {"previousTotalVote": 117, "previousTotalVotePercent": 0.012796437121917234, "candidate": null, "previousCandidate": null, "no": 0, "name": "MEHMET HOCAOĞLU", "totalVote": 63, "totalVotePercent": 0.006901152492466242, "url": ""}, {"previousTotalVote": 117, "previousTotalVotePercent": 0.012796437121917234, "candidate": null, "previousCandidate": null, "no": 0, "name": "HAYDAR KEMAL BAŞKINACI", "totalVote": 38, "totalVotePercent": 0.004162599916090749, "url": ""}], "councilPartyMap": [{"chest": {"totalChest": 91, "totalOpenChestPercent": 100, "openChest": 91, "totalVoter": 22511, "totalVote": 19295, "validVote": 17843, "invalidVote": 1452, "totalJoinPercent": 85.71365110390475}, "details": [{"candidate": {"no": "0", "name": "Mehmet Özdemir", "partyNo": "11", "url": "/mhp/gaziantep/araban/mehmet-ozdemir-belediye-baskani-adayi/"}, "previousTotalVote": null, "previousTotalVotePercent": null, "no": 11, "name": "MHP", "totalVote": 5779, "totalVotePercent": 32.388051336658634, "url": "/mhp-yerel-secim-sonuclari/"}, {"candidate": {"no": "0", "name": "Hasan Doğru", "partyNo": "10", "url": "/yeniden-refah/gaziantep/araban/hasan-dogru-belediye-baskani-adayi/"}, "previousTotalVote": null, "previousTotalVotePercent": null, "no": 10, "name": "Yeniden Refah", "totalVote": 4642, "totalVotePercent": 26.015804517177603, "url": "/yeniden-refah-yerel-secim-sonuclari/"}], "winner": {"candidate": {"no": "0", "name": "Mehmet Özdemir", "partyNo": "11", "url": "/mhp/gaziantep/araban/mehmet-ozdemir-belediye-baskani-adayi/"}, "previousTotalVote": null, "previousTotalVotePercent": null, "no": 11, "name": "MHP", "totalVote": 5779, "totalVotePercent": 32.388051336658634, "url": "/mhp-yerel-secim-sonuclari/"}, "previousWinner": null, "councilPartySummaries": [], "allParties": null, "towns": [], "no": 38, "name": "ARABAN", "totalVote": 0, "totalVotePercent": 0, "url": "/gaziantep-araban-ilcesi-yerel-secim-sonuclari/"}, {"chest": {"totalChest": 162, "totalOpenChestPercent": 100, "openChest": 162, "totalVoter": 44372, "totalVote": 35983, "validVote": 33748, "invalidVote": 2235, "totalJoinPercent": 81.09393311097088}, "details": [{"candidate": {"no": "0", "name": "Kemal Vural", "partyNo": "9", "url": "/ak-parti/gaziantep/islahiye/kemal-vural-belediye-baskani-adayi/"}, "previousTotalVote": null, "previousTotalVotePercent": null, "no": 9, "name": "AK Parti", "totalVote": 12126, "totalVotePercent": 35.931018134407964, "url": "/ak-parti-yerel-secim-sonuclari/"}, {"candidate": {"no": "0", "name": "Okan Öztürk", "partyNo": "21", "url": "#"}, "previousTotalVote": null, "previousTotalVotePercent": null, "no": 21, "name": "CHP", "totalVote": 9944, "totalVotePercent": 29.465449804432854, "url": "/chp-yerel-secim-sonuclari/"}], "winner": {"candidate": {"no": "0", "name": "Kemal Vural", "partyNo": "9", "url": "/ak-parti/gaziantep/islahiye/kemal-vural-belediye-baskani-adayi/"}, "previousTotalVote": null, "previousTotalVotePercent": null, "no": 9, "name": "AK Parti", "totalVote": 12126, "totalVotePercent": 35.931018134407964, "url": "/ak-parti-yerel-secim-sonuclari/"}, "previousWinner": null, "councilPartySummaries": [], "allParties": null, "towns": [], "no": 312, "name": "İSLAHİYE", "totalVote": 0, "totalVotePercent": 0, "url": "/gaziantep-islahiye-ilcesi-yerel-secim-sonuclari/"}, {"chest": {"totalChest": 46, "totalOpenChestPercent": 100, "openChest": 46, "totalVoter": 7334, "totalVote": 6686, "validVote": 6349, "invalidVote": 337, "totalJoinPercent": 91.16443959640033}, "details": [{"candidate": {"no": "0", "name": "Mustafa Güzel", "partyNo": "21", "url": "/chp/gaziantep/karkamis/mustafa-guzel-belediye-baskani-adayi/"}, "previousTotalVote": null, "previousTotalVotePercent": null, "no": 21, "name": "CHP", "totalVote": 2403, "totalVotePercent": 37.84848007560246, "url": "/chp-yerel-secim-sonuclari/"}, {"candidate": {"no": "0", "name": "Bülent Tiryaki", "partyNo": "11", "url": "/mhp/gaziantep/karkamis/bulent-tiryaki-belediye-baskani-adayi/"}, "previousTotalVote": null, "previousTotalVotePercent": null, "no": 11, "name": "MHP", "totalVote": 2354, "totalVotePercent": 37.07670499291227, "url": "/mhp-yerel-secim-sonuclari/"}], "winner": {"candidate": {"no": "0", "name": "Mustafa Güzel", "partyNo": "21", "url": "/chp/gaziantep/karkamis/mustafa-guzel-belediye-baskani-adayi/"}, "previousTotalVote": null, "previousTotalVotePercent": null, "no": 21, "name": "CHP", "totalVote": 2403, "totalVotePercent": 37.84848007560246, "url": "/chp-yerel-secim-sonuclari/"}, "previousWinner": null, "councilPartySummaries": [], "allParties": null, "towns": [], "no": 849, "name": "KARKAMIŞ", "totalVote": 0, "totalVotePercent": 0, "url": "/gaziantep-karkamis-ilcesi-yerel-secim-sonuclari/"}, {"chest": {"totalChest": 345, "totalOpenChestPercent": 100, "openChest": 345, "totalVoter": 97181, "totalVote": 79244, "validVote": 74054, "invalidVote": 5190, "totalJoinPercent": 81.54268838558977}, "details": [{"candidate": {"no": "0", "name": "Ali Doğan", "partyNo": "21", "url": "#"}, "previousTotalVote": null, "previousTotalVotePercent": null, "no": 21, "name": "CHP", "totalVote": 25780, "totalVotePercent": 34.81243416965998, "url": "/chp-yerel-secim-sonuclari/"}, {"candidate": {"no": "0", "name": "Haci Fevzi Akdoğan", "partyNo": "9", "url": "/ak-parti/gaziantep/nizip/haci-fevzi-akdogan-belediye-baskani-adayi/"}, "previousTotalVote": null, "previousTotalVotePercent": null, "no": 9, "name": "AK Parti", "totalVote": 24922, "totalVotePercent": 33.653820185270206, "url": "/ak-parti-yerel-secim-sonuclari/"}], "winner": {"candidate": {"no": "0", "name": "Ali Doğan", "partyNo": "21", "url": "#"}, "previousTotalVote": null, "previousTotalVotePercent": null, "no": 21, "name": "CHP", "totalVote": 25780, "totalVotePercent": 34.81243416965998, "url": "/chp-yerel-secim-sonuclari/"}, "previousWinner": null, "councilPartySummaries": [], "allParties": null, "towns": [], "no": 439, "name": "NİZİP", "totalVote": 0, "totalVotePercent": 0, "url": "/gaziantep-nizip-ilcesi-yerel-secim-sonuclari/"}, {"chest": {"totalChest": 105, "totalOpenChestPercent": 100, "openChest": 105, "totalVoter": 27485, "totalVote": 21662, "validVote": 20508, "invalidVote": 1154, "totalJoinPercent": 78.8138984900855}, "details": [{"candidate": {"no": "0", "name": "Mehmet Yıldırır", "partyNo": "9", "url": "/ak-parti/gaziantep/nurdagi/mehmet-yildirir-belediye-baskani-adayi/"}, "previousTotalVote": null, "previousTotalVotePercent": null, "no": 9, "name": "AK Parti", "totalVote": 9592, "totalVotePercent": 46.77199141798322, "url": "/ak-parti-yerel-secim-sonuclari/"}, {"candidate": {"no": "0", "name": "Hasan Dilek", "partyNo": "10", "url": "/yeniden-refah/gaziantep/nurdagi/hasan-dilek-belediye-baskani-adayi/"}, "previousTotalVote": null, "previousTotalVotePercent": null, "no": 10, "name": "Yeniden Refah", "totalVote": 8636, "totalVotePercent": 42.11039594304662, "url": "/yeniden-refah-yerel-secim-sonuclari/"}], "winner": {"candidate": {"no": "0", "name": "Mehmet Yıldırır", "partyNo": "9", "url": "/ak-parti/gaziantep/nurdagi/mehmet-yildirir-belediye-baskani-adayi/"}, "previousTotalVote": null, "previousTotalVotePercent": null, "no": 9, "name": "AK Parti", "totalVote": 9592, "totalVotePercent": 46.77199141798322, "url": "/ak-parti-yerel-secim-sonuclari/"}, "previousWinner": null, "councilPartySummaries": [], "allParties": null, "towns": [], "no": 867, "name": "NURDAĞI", "totalVote": 0, "totalVotePercent": 0, "url": "/gaziantep-nurdagi-ilcesi-yerel-secim-sonuclari/"}, {"chest": {"totalChest": 127, "totalOpenChestPercent": 100, "openChest": 127, "totalVoter": 24784, "totalVote": 21257, "validVote": 19855, "invalidVote": 1402, "totalJoinPercent": 85.76904454486765}, "details": [{"candidate": {"no": "0", "name": "Mehmet Sait Kılıç", "partyNo": "11", "url": "/mhp/gaziantep/oguzeli/mehmet-sait-kilic-belediye-baskani-adayi/"}, "previousTotalVote": null, "previousTotalVotePercent": null, "no": 11, "name": "MHP", "totalVote": 6617, "totalVotePercent": 33.32661798035759, "url": "/mhp-yerel-secim-sonuclari/"}, {"candidate": {"no": "0", "name": "Bekir Öztekin", "partyNo": "10", "url": "#"}, "previousTotalVote": null, "previousTotalVotePercent": null, "no": 10, "name": "Yeniden Refah", "totalVote": 6579, "totalVotePercent": 33.13523042054898, "url": "/yeniden-refah-yerel-secim-sonuclari/"}], "winner": {"candidate": {"no": "0", "name": "Mehmet Sait Kılıç", "partyNo": "11", "url": "/mhp/gaziantep/oguzeli/mehmet-sait-kilic-belediye-baskani-adayi/"}, "previousTotalVote": null, "previousTotalVotePercent": null, "no": 11, "name": "MHP", "totalVote": 6617, "totalVotePercent": 33.32661798035759, "url": "/mhp-yerel-secim-sonuclari/"}, "previousWinner": null, "councilPartySummaries": [], "allParties": null, "towns": [], "no": 442, "name": "OĞUZELİ", "totalVote": 0, "totalVotePercent": 0, "url": "/gaziantep-oguzeli-ilcesi-yerel-secim-sonuclari/"}, {"chest": {"totalChest": 1840, "totalOpenChestPercent": 100, "openChest": 1840, "totalVoter": 609600, "totalVote": 412076, "validVote": 388629, "invalidVote": 23447, "totalJoinPercent": 67.5977690288714}, "details": [{"candidate": {"no": "0", "name": "Mehmet İhsan Tahmazoğlu", "partyNo": "9", "url": "/ak-parti/gaziantep/sahinbey/mehmet-ihsan-tahmazoglu-belediye-baskani-adayi/"}, "previousTotalVote": null, "previousTotalVotePercent": null, "no": 9, "name": "AK Parti", "totalVote": 176520, "totalVotePercent": 45.42121148962121, "url": "/ak-parti-yerel-secim-sonuclari/"}, {"candidate": {"no": "0", "name": "Arkın Bereketoğlu", "partyNo": "21", "url": "#"}, "previousTotalVote": null, "previousTotalVotePercent": null, "no": 21, "name": "CHP", "totalVote": 93866, "totalVotePercent": 24.153112608683347, "url": "/chp-yerel-secim-sonuclari/"}], "winner": {"candidate": {"no": "0", "name": "Mehmet İhsan Tahmazoğlu", "partyNo": "9", "url": "/ak-parti/gaziantep/sahinbey/mehmet-ihsan-tahmazoglu-belediye-baskani-adayi/"}, "previousTotalVote": null, "previousTotalVotePercent": null, "no": 9, "name": "AK Parti", "totalVote": 176520, "totalVotePercent": 45.42121148962121, "url": "/ak-parti-yerel-secim-sonuclari/"}, "previousWinner": null, "councilPartySummaries": [], "allParties": null, "towns": [], "no": 734, "name": "ŞAHİNBEY", "totalVote": 0, "totalVotePercent": 0, "url": "/gaziantep-sahinbey-ilcesi-yerel-secim-sonuclari/"}, {"chest": {"totalChest": 1627, "totalOpenChestPercent": 100, "openChest": 1627, "totalVoter": 535964, "totalVote": 368133, "validVote": 339493, "invalidVote": 28640, "totalJoinPercent": 68.68614309916337}, "details": [{"candidate": {"no": "0", "name": "Umut Yılmaz", "partyNo": "21", "url": "#"}, "previousTotalVote": null, "previousTotalVotePercent": null, "no": 21, "name": "CHP", "totalVote": 114125, "totalVotePercent": 33.616304312607326, "url": "/chp-yerel-secim-sonuclari/"}, {"candidate": {"no": "0", "name": "Muhammet Rıdvan Fadıloğlu", "partyNo": "9", "url": "/ak-parti/gaziantep/sehitkamil/muhammet-ridvan-fadiloglu-belediye-baskani-adayi/"}, "previousTotalVote": null, "previousTotalVotePercent": null, "no": 9, "name": "AK Parti", "totalVote": 96516, "totalVotePercent": 28.42945215365265, "url": "/ak-parti-yerel-secim-sonuclari/"}], "winner": {"candidate": {"no": "0", "name": "Umut Yılmaz", "partyNo": "21", "url": "#"}, "previousTotalVote": null, "previousTotalVotePercent": null, "no": 21, "name": "CHP", "totalVote": 114125, "totalVotePercent": 33.616304312607326, "url": "/chp-yerel-secim-sonuclari/"}, "previousWinner": null, "councilPartySummaries": [], "allParties": null, "towns": [], "no": 737, "name": "ŞEHİTKAMİL", "totalVote": 0, "totalVotePercent": 0, "url": "/gaziantep-sehitkamil-ilcesi-yerel-secim-sonuclari/"}, {"chest": {"totalChest": 63, "totalOpenChestPercent": 100, "openChest": 63, "totalVoter": 14635, "totalVote": 13112, "validVote": 12412, "invalidVote": 700, "totalJoinPercent": 89.59344038264435}, "details": [{"candidate": {"no": "0", "name": "Mustafa Kemal Sakaroğlu", "partyNo": "9", "url": "/ak-parti/gaziantep/yavuzeli/mustafa-kemal-sakaroglu-belediye-baskani-adayi/"}, "previousTotalVote": null, "previousTotalVotePercent": null, "no": 9, "name": "AK Parti", "totalVote": 4073, "totalVotePercent": 32.81501772478247, "url": "/ak-parti-yerel-secim-sonuclari/"}, {"candidate": {"no": "0", "name": "Mehmet Kaya", "partyNo": "10", "url": "#"}, "previousTotalVote": null, "previousTotalVotePercent": null, "no": 10, "name": "Yeniden Refah", "totalVote": 3997, "totalVotePercent": 32.20270705768611, "url": "/yeniden-refah-yerel-secim-sonuclari/"}], "winner": {"candidate": {"no": "0", "name": "Mustafa Kemal Sakaroğlu", "partyNo": "9", "url": "/ak-parti/gaziantep/yavuzeli/mustafa-kemal-sakaroglu-belediye-baskani-adayi/"}, "previousTotalVote": null, "previousTotalVotePercent": null, "no": 9, "name": "AK Parti", "totalVote": 4073, "totalVotePercent": 32.81501772478247, "url": "/ak-parti-yerel-secim-sonuclari/"}, "previousWinner": null, "councilPartySummaries": [], "allParties": null, "towns": [], "no": 613, "name": "YAVUZELİ", "totalVote": 0, "totalVotePercent": 0, "url": "/gaziantep-yavuzeli-ilcesi-yerel-secim-sonuclari/"}], "partiesMostVotesCities": null, "numberofWonByParties": [{"wonCount": 3, "no": 9, "name": "AK Parti", "totalVote": 11568, "totalVotePercent": 1.2586568016755977, "url": "/ak-parti-yerel-secim-sonuclari/"}, {"wonCount": 3, "no": 21, "name": "CHP", "totalVote": 28182, "totalVotePercent": 3.066343878355956, "url": "/chp-yerel-secim-sonuclari/"}, {"wonCount": 2, "no": 10, "name": "Yeniden Refah", "totalVote": 7496, "totalVotePercent": 0.8156026439626799, "url": "/yeniden-refah-yerel-secim-sonuclari/"}, {"wonCount": 1, "no": 11, "name": "MHP", "totalVote": 5992, "totalVotePercent": 0.6519598509370835, "url": "/mhp-yerel-secim-sonuclari/"}], "candidateChangeOverview": {"currentWinner": {"candidate": {"no": "0", "name": "Fatma Şahin", "partyNo": "9", "url": "/ak-parti/gaziantep/fatma-sahin-belediye-baskani-adayi/"}, "previousTotalVote": null, "previousTotalVotePercent": null, "no": 9, "name": "AK Parti", "totalVote": 358590, "totalVotePercent": 38.82886453264379, "url": "/ak-parti-yerel-secim-sonuclari/"}, "previousWinner": {"candidate": {"no": "0", "name": "Fatma Şahin", "partyNo": "9", "url": null}, "previousTotalVote": null, "previousTotalVotePercent": null, "no": 9, "name": "AK Parti", "totalVote": 494905, "totalVotePercent": 53.973130399030694, "url": "/ak-parti-yerel-secim-sonuclari/"}}, "updateDate": "21:26", "mayorVersion": "01 Nisan 2024 21:26", "chest": {"totalChest": 206806, "totalOpenChestPercent": 100, "openChest": 206806, "totalVoter": 61430934, "totalVote": 48256541, "validVote": 46046499, "invalidVote": 2210042, "totalJoinPercent": 78.55413853873685}, "chestCouncil": null, "currentElectionYear": "2024", "previousElectionYear": "2019", "displayName": "31 Mart 2024", "previousDisplayName": "31 Mart 2019", "isBannerActive": false, "showDataDiff": true}